Workbook

Sheet US Overview
A1: US FISCAL ACCOUNTING — RAW -> BVAR -> RECURSION -> PROJECTION
A3: THE TARGET CONCEPT
A4: User's level form | B4: B_t = Exp_t - Rev_t + (1 + i_eff_t)*B_{t-1}, then d_t = B_t / GDP_t. Exp = PRIMARY expenditure (EXCLUDES interest). Rev = revenue. i_eff = effective rate on the debt stock. B = debt stock (level). The interest cost sits entirely in the (1+i_eff)*B_{t-1} term. d = B/GDP.
A5: App's ratio form (per quarter) | B5: d_t = d_{t-1}*(1 + i_eff/400)/(1 + gNomQ/100) - pb/4 (% of GDP; i_eff %/yr; gNomQ %/quarter; pb = rev - primexp). This is the user's level form rewritten in ratio space and quarterised - the SAME identity. The 'Fiscal Arithmetic' sheet proves the two land on the identical debt/GDP, column by column.
A7: THE THREE BVAR FISCAL DRIVERS (estimated)
A8: FREV_GDP | B8: Revenue / GDP * 100 (% of GDP). BVAR 'lin' variable.
A9: FPEXP_GDP | B9: (Expenditure - interest) / GDP * 100 = PRIMARY expenditure / GDP (% of GDP). 'lin'.
A10: DSVC | B10: Debt service / GDP * 100 = net interest / LAGGED GDP (% of GDP). 'lin'. THIS is forecast by the BVAR; the effective rate i_eff is BACKED OUT from it as i_eff = DSVC*100 / d_{t-1}.
A11: (internal) EFFI | B11: Effective interest rate = net interest / LAGGED debt stock * 100 (% p.a.). DSVC = EFFI * d_{t-1}/100, i.e. debt service = the effective rate applied to last quarter's debt ratio.
A13: THE FIVE SHEETS PER COUNTRY
A14: Raw Data | B14: the raw series in levels, with charts.
A15: Construction | B15: builds FREV_GDP, FPEXP_GDP, EFFI and DSVC from the raw cells with LIVE formulas.
A16: Fiscal Arithmetic | B16: reconstructs HISTORICAL debt/GDP from the flows (back-cast check vs observed).
A17: Projection | B17: how the BVAR projects DSVC (debt service) and debt/GDP AHEAD, with 16/84 bands.
A19: RAW SERIES & SOURCES
A20: Raw series (role) | B20: Source ID / provenance, units
A21: nominal GDP | B21: FRED: GDP - nominal GDP, $bn SAAR
A22: federal receipts | B22: FRED: FGRECPT - federal current receipts, $bn SAAR
A23: federal expenditure | B23: FRED: FGEXPND - federal current expenditures (INCL. interest), $bn SAAR
A24: federal net interest | B24: FRED: A091RC1Q027SBEA - federal interest payments, $bn SAAR
A25: gross federal debt | B25: FRED: GFDEGDQ188S - gross federal debt as % of GDP (the d0 anchor)
A27: UNIT CONVENTIONS
A28: SAAR (US flows) | B28: GDP/FGRECPT/FGEXPND/A091 are Seasonally-Adjusted ANNUAL RATES: each quarter already states an annual $-rate, so a ratio is flow_t / GDP_t with NO *4.
A29: Quarterly levels (UK flows) | B29: ONS revenue/expenditure/interest are quarterly LEVELS (GBP m, not annualised), so the ratio uses a 4-QUARTER TRAILING SUM: 4q-sum(flow)/4q-sum(GDP).
A30: % of GDP (annual ratio) | B30: FREV_GDP, FPEXP_GDP, DSVC are annual ratios, e.g. 18 means 18% of GDP. Carried in the BVAR as 'lin' (level) variables.
A31: Effective rate | B31: EFFI is %/year on the debt STOCK (e.g. 3 = 3%/yr); NOT the policy or market yield.
A32: Debt / GDP (d) | B32: d, d0 in %, e.g. 100 = 100% of GDP. This workbook's US d0 = 122.5682%.
A33: Nominal growth gNomQ | B33: %/QUARTER. US: from SAAR GDP (already annual). UK: from the 4q-GDP base (same base the ratio uses). The forecast uses Delta(real 100*log GDP) + Delta(deflator 100*log).
A35: COVID NOTE (US only): the deployed BVAR linearly interpolates FPEXP_GDP across the SAME 7 quarters it carries, 2020Q2-2021Q4, to remove the CARES/ARP emergency-spending spike (raw 2020Q2 FPEXP ~42% of GDP vs a ~20% norm). US flows are SAAR, so there is NO annual-window lag: the treated quarters ARE the BVAR's quarters. The Construction sheet shows BOTH the raw (no-COVID) FPEXP and the value that actually entered the BVAR. FREV and DSVC are untreated. The UK gets no COVID treatment (raw == deployed).
A36: SPOT-CHECK vs the deployed BVAR app/public/data/bvar/US: US 2025Q4 (last history): FREV_GDP=18.7715, FPEXP_GDP=20.2281, DSVC=3.9472 - MATCH historical.json cols 33/34/35 exactly. All 40 quarters match to <1e-4, except the 7 COVID quarters 2020Q2-2021Q4 where the into-BVAR FPEXP is interpolated (raw 2020Q2 FPEXP=41.97 vs into-BVAR 20.04). BVAR projects DSVC 3.96 -> 4.92% of GDP over 20 quarters (see US Projection).

Sheet US Raw Data
A1: US RAW DATA - FRED quarterly (SAAR flows; debt as % of GDP)
A3: Date | B3: GDP ($bn, SAAR) | C3: FGRECPT receipts ($bn, SAAR) | D3: FGEXPND expenditure ($bn, SAAR) | E3: A091 net interest ($bn, SAAR) | F3: GFDEGDQ188S gross debt (% of GDP)
B4: FRED: GDP | C4: FRED: FGRECPT | D4: FRED: FGEXPND | E4: FRED: A091RC1Q027SBEA | F4: FRED: GFDEGDQ188S
A5: 1998-Q2 | B5: 8969.699 | C5: 1771.548 | D5: 1781.911 | E5: 367.648 | F5: 61.85196
A6: 1998-Q3 | B6: 9121.097 | C6: 1808.447 | D6: 1788.538 | E6: 366.204 | F6: 60.58693
A7: 1998-Q4 | B7: 9293.991 | C7: 1835.085 | D7: 1814.518 | E7: 360.088 | F7: 60.40696
A8: 1999-Q1 | B8: 9411.682 | C8: 1860.002 | D8: 1811.988 | E8: 352.596 | F8: 60.04894
A9: 1999-Q2 | B9: 9526.21 | C9: 1885.184 | D9: 1816.961 | E9: 352.141 | F9: 59.19227
A10: 1999-Q3 | B10: 9686.626 | C10: 1914.862 | D10: 1843.205 | E10: 351.073 | F10: 58.39258
A11: 1999-Q4 | B11: 9900.169 | C11: 1963.756 | D11: 1875.154 | E11: 352.925 | F11: 58.34336
A12: 2000-Q1 | B12: 10002.179 | C12: 2041.764 | D12: 1866.308 | E12: 354.822 | F12: 57.72134
A13: 2000-Q2 | B13: 10247.72 | C13: 2056.279 | D13: 1908.645 | E13: 354.109 | F13: 55.48491
A14: 2000-Q3 | B14: 10318.165 | C14: 2076.268 | D14: 1918.617 | E14: 352.877 | F14: 54.99213
A15: 2000-Q4 | B15: 10435.744 | C15: 2096.796 | D15: 1938.796 | E15: 353.105 | F15: 54.2579
A16: 2001-Q1 | B16: 10470.231 | C16: 2111.058 | D16: 1982.626 | E16: 345.479 | F16: 55.14434
... A115: 2025-Q4 | B115: 31422.526 | C115: 5898.479 | D115: 7583.663 | E115: 1227.495 | F115: 122.56815

Sheet US Raw Data_nsa
A1: US RAW DATA - FRED quarterly (SAAR flows; debt as % of GDP)
A3: Date | B3: Gross Domestic Product (NA000334Q),Millions of Dollars, Not Seasonally Adjusted | C3: Federal Government Current Receipts (NA000304Q), Millions of Dollars, Not Seasonally Adjusted | D3: Federal Government: Current Expenditures (NA000283Q), Millions of Dollars, Not Seasonally Adjusted | E3: Federal government current expenditures: Interest payments (NA000308Q), Millions of Dollars, Not Seasonally Adjusted | F3: GFDEBTN - Federal Debt: Total Public Debt (GFDEBTN), Millions of Dollars, Not Seasonally Adjusted
B4: FRED: NA000334Q | C4: FRED: NA000304Q | D4: FRED: NA000283Q | E4: FRED: NA000308Q | F4: FRED: GFDEBTN
A5: 1998-Q2 | B5: 2249908 | C5: 455865 | D5: 445251 | E5: 91910 | F5: 5547935
A6: 1998-Q3 | B6: 2281422 | C6: 456297 | D6: 443702 | E6: 91551 | F6: 5526193
A7: 1998-Q4 | B7: 2370677 | C7: 450491 | D7: 460154 | E7: 90022 | F7: 5614217
A8: 1999-Q1 | B8: 2293136 | C8: 451584 | D8: 448286 | E8: 88149 | F8: 5651615
A9: 1999-Q2 | B9: 2388422 | C9: 486768 | D9: 456605 | E9: 88035 | F9: 5638780
A10: 1999-Q3 | B10: 2423648 | C10: 483561 | D10: 458196 | E10: 87768 | F10: 5656271
A11: 1999-Q4 | B11: 2524828 | C11: 484037 | D11: 473741 | E11: 88231 | F11: 5776091
A12: 2000-Q1 | B12: 2448892 | C12: 499364 | D12: 468041 | E12: 88705 | F12: 5773392
A13: 2000-Q2 | B13: 2569266 | C13: 531105 | D13: 479183 | E13: 88527 | F13: 5685938
A14: 2000-Q3 | B14: 2577927 | C14: 522953 | D14: 472437 | E14: 88219 | F14: 5674179
A15: 2000-Q4 | B15: 2655636 | C15: 514356 | D15: 488430 | E15: 88276 | F15: 5662216
A16: 2001-Q1 | B16: 2562488 | C16: 511352 | D16: 497170 | E16: 86370 | F16: 5773740
... A115: 2025-Q4 | B115: 7971751 | C115: 1501013 | D115: 1892982 | E115: 306874 | F115: 38514009
B116: 7764730 | D116: 1914942 | E116: 304734

Sheet UScalc_nsa
A1: Quarter | B1: GDPN | C1: TAX | D1: GEXP+INTEXP | E1: INTEXP | F1: GEXP | G1: DEBT | H1: DEBTCheck1 | I1: RESID | J1: DEBTCheck2 | K1: DEBTCheck3 | M1: GEXPSHR | N1: TAXSHR | O1: DEBTG | P1: DEBTGL | Q1: Ieff | R1: FFLOWSHR | S1: DEBTcheck Static | T1: DEBTcheck Dynamic | AF1: Is DEBTG end of period?
A2: ='US Raw Data_nsa'!A5 -> 1998-Q2 | B2: ='US Raw Data_nsa'!B5 -> 2249908 | C2: ='US Raw Data_nsa'!C5 -> 455865 | D2: ='US Raw Data_nsa'!D5 -> 445251 | E2: ='US Raw Data_nsa'!E5 -> 91910 | F2: =D2-E2 -> 353341 | G2: ='US Raw Data_nsa'!F5 -> 5547935 | M2: =400*F2/(4*B2) -> 15.704687 | N2: =400*C2/(4*B2) -> 20.261495 | O2: =100*G2/(4*B2) -> 61.646243 | P2: NaN | Q2: NaN | R2: NaN | T2: GDP(t-1) | U2: GDP(t) | AF2: Are expenditures includig or excluding interest rate component?
A3: ='US Raw Data_nsa'!A6 -> 1998-Q3 | B3: ='US Raw Data_nsa'!B6 -> 2281422 | C3: ='US Raw Data_nsa'!C6 -> 456297 | D3: ='US Raw Data_nsa'!D6 -> 443702 | E3: ='US Raw Data_nsa'!E6 -> 91551 | F3: =D3-E3 -> 352151 | G3: ='US Raw Data_nsa'!F6 -> 5526193 | H3: =F3-C3+E3+G2 -> 5535340 | I3: =G3-H3 -> -9147 | J3: =F3-C3+E3+G2 -> 5535340 | K3: =F3-C3+E3+I3+G2 -> 5526193 | M3: =400*F3/(4*B3) -> 15.435592 | N3: =400*C3/(4*B3) -> 20.000552 | O3: =100*G3/(4*B3) -> 60.556453 | P3: =100*G2/(4*B3) -> 60.794704 | Q3: =400*E3/(4*B3)*(1/(P3/100)) -> 6.6007262 | R3: =400*I3/(4*B3) -> -0.40093415 | S3: =(1/4)*(M3-N3+R3)+(1+(Q3/400))*P3 -> 60.556453 | T3: =(1/4)*(M3-N3+R3)+(1+(Q3/400))*P3 -> 60.556453
A4: ='US Raw Data_nsa'!A7 -> 1998-Q4 | B4: ='US Raw Data_nsa'!B7 -> 2370677 | C4: ='US Raw Data_nsa'!C7 -> 450491 | D4: ='US Raw Data_nsa'!D7 -> 460154 | E4: ='US Raw Data_nsa'!E7 -> 90022 | F4: =D4-E4 -> 370132 | G4: ='US Raw Data_nsa'!F7 -> 5614217 | H4: =F4-C4+E4+G3 -> 5535856 | I4: =G4-H4 -> 78361 | J4: =F4-C4+E4+J3 -> 5545003 | K4: =F4-C4+E4+I4+K3 -> 5614217 | M4: =400*F4/(4*B4) -> 15.612924 | N4: =400*C4/(4*B4) -> 19.002631 | O4: =100*G4/(4*B4) -> 59.204786 | P4: =100*G3/(4*B4) -> 58.276528 | Q4: =400*E4/(4*B4)*(1/(P4/100)) -> 6.5160229 | R4: =400*I4/(4*B4) -> 3.3054271 | S4: =(1/4)*(M4-N4+R4)+(1+(Q4/400))*P4 -> 59.204786 | T4: =(1/4)*(M4-N4+R4)+(1+(Q4/400))*T3 -> 61.521852 | U4: =T4*(B3/B4) -> 59.20558
A5: ='US Raw Data_nsa'!A8 -> 1999-Q1 | B5: ='US Raw Data_nsa'!B8 -> 2293136 | C5: ='US Raw Data_nsa'!C8 -> 451584 | D5: ='US Raw Data_nsa'!D8 -> 448286 | E5: ='US Raw Data_nsa'!E8 -> 88149 | F5: =D5-E5 -> 360137 | G5: ='US Raw Data_nsa'!F8 -> 5651615 | H5: =F5-C5+E5+G4 -> 5610919 | I5: =G5-H5 -> 40696 | J5: =F5-C5+E5+J4 -> 5541705 | K5: =F5-C5+E5+I5+K4 -> 5651615 | M5: =400*F5/(4*B5) -> 15.705 | N5: =400*C5/(4*B5) -> 19.692857 | O5: =100*G5/(4*B5) -> 61.614477 | P5: =100*G4/(4*B5) -> 61.20676 | Q5: =400*E5/(4*B5)*(1/(P5/100)) -> 6.2804127 | R5: =400*I5/(4*B5) -> 1.7746876 | S5: =(1/4)*(M5-N5+R5)+(1+(Q5/400))*P5 -> 61.614477 | T5: =(1/4)*(M5-N5+R5)+(1+(Q5/400))*U4 -> 59.581876 | U5: =T5*(B4/B5) -> 61.596601
A6: ='US Raw Data_nsa'!A9 -> 1999-Q2 | B6: ='US Raw Data_nsa'!B9 -> 2388422 | C6: ='US Raw Data_nsa'!C9 -> 486768 | D6: ='US Raw Data_nsa'!D9 -> 456605 | E6: ='US Raw Data_nsa'!E9 -> 88035 | F6: =D6-E6 -> 368570 | G6: ='US Raw Data_nsa'!F9 -> 5638780 | H6: =F6-C6+E6+G5 -> 5621452 | I6: =G6-H6 -> 17328 | J6: =F6-C6+E6+J5 -> 5511542 | K6: =F6-C6+E6+I6+K5 -> 5638780 | M6: =400*F6/(4*B6) -> 15.431528 | N6: =400*C6/(4*B6) -> 20.380318 | O6: =100*G6/(4*B6) -> 59.022024 | P6: =100*G5/(4*B6) -> 59.15637 | Q6: =400*E6/(4*B6)*(1/(P6/100)) -> 6.2307854 | R6: =400*I6/(4*B6) -> 0.72549993 | S6: =(1/4)*(M6-N6+R6)+(1+(Q6/400))*P6 -> 59.022024 | T6: =(1/4)*(M6-N6+R6)+(1+(Q6/400))*U5 -> 61.500266 | U6: =T6*(B5/B6) -> 59.046715
A7: ='US Raw Data_nsa'!A10 -> 1999-Q3 | B7: ='US Raw Data_nsa'!B10 -> 2423648 | C7: ='US Raw Data_nsa'!C10 -> 483561 | D7: ='US Raw Data_nsa'!D10 -> 458196 | E7: ='US Raw Data_nsa'!E10 -> 87768 | F7: =D7-E7 -> 370428 | G7: ='US Raw Data_nsa'!F10 -> 5656271 | H7: =F7-C7+E7+G6 -> 5613415 | I7: =G7-H7 -> 42856 | J7: =F7-C7+E7+J6 -> 5486177 | K7: =F7-C7+E7+I7+K6 -> 5656271 | M7: =400*F7/(4*B7) -> 15.283903 | N7: =400*C7/(4*B7) -> 19.951783 | O7: =100*G7/(4*B7) -> 58.344601 | P7: =100*G6/(4*B7) -> 58.164181 | Q7: =400*E7/(4*B7)*(1/(P7/100)) -> 6.2260276 | R7: =400*I7/(4*B7) -> 1.7682436 | S7: =(1/4)*(M7-N7+R7)+(1+(Q7/400))*P7 -> 58.344601 | T7: =(1/4)*(M7-N7+R7)+(1+(Q7/400))*U6 -> 59.240872 | U7: =T7*(B6/B7) -> 58.379848
A8: ='US Raw Data_nsa'!A11 -> 1999-Q4 | B8: ='US Raw Data_nsa'!B11 -> 2524828 | C8: ='US Raw Data_nsa'!C11 -> 484037 | D8: ='US Raw Data_nsa'!D11 -> 473741 | E8: ='US Raw Data_nsa'!E11 -> 88231 | F8: =D8-E8 -> 385510 | G8: ='US Raw Data_nsa'!F11 -> 5776091 | H8: =F8-C8+E8+G7 -> 5645975 | I8: =G8-H8 -> 130116 | J8: =F8-C8+E8+J7 -> 5475881 | K8: =F8-C8+E8+I8+K7 -> 5776091 | M8: =400*F8/(4*B8) -> 15.268763 | N8: =400*C8/(4*B8) -> 19.171088 | O8: =100*G8/(4*B8) -> 57.192916 | P8: =100*G7/(4*B8) -> 56.006498 | Q8: =400*E8/(4*B8)*(1/(P8/100)) -> 6.2395172 | R8: =400*I8/(4*B8) -> 5.15346 | S8: =(1/4)*(M8-N8+R8)+(1+(Q8/400))*P8 -> 57.192916 | T8: =(1/4)*(M8-N8+R8)+(1+(Q8/400))*U7 -> 59.603287 | U8: =T8*(B7/B8) -> 57.214744
A9: ='US Raw Data_nsa'!A12 -> 2000-Q1 | B9: ='US Raw Data_nsa'!B12 -> 2448892 | C9: ='US Raw Data_nsa'!C12 -> 499364 | D9: ='US Raw Data_nsa'!D12 -> 468041 | E9: ='US Raw Data_nsa'!E12 -> 88705 | F9: =D9-E9 -> 379336 | G9: ='US Raw Data_nsa'!F12 -> 5773392 | H9: =F9-C9+E9+G8 -> 5744768 | I9: =G9-H9 -> 28624 | J9: =F9-C9+E9+J8 -> 5444558 | K9: =F9-C9+E9+I9+K8 -> 5773392 | M9: =400*F9/(4*B9) -> 15.490107 | N9: =400*C9/(4*B9) -> 20.391426 | O9: =100*G9/(4*B9) -> 58.938818 | P9: =100*G8/(4*B9) -> 58.966371 | Q9: =400*E9/(4*B9)*(1/(P9/100)) -> 6.1429088 | R9: =400*I9/(4*B9) -> 1.1688551 | S9: =(1/4)*(M9-N9+R9)+(1+(Q9/400))*P9 -> 58.938818 | T9: =(1/4)*(M9-N9+R9)+(1+(Q9/400))*U8 -> 57.16029 | U9: =T9*(B8/B9) -> 58.932734
A10: ='US Raw Data_nsa'!A13 -> 2000-Q2 | B10: ='US Raw Data_nsa'!B13 -> 2569266 | C10: ='US Raw Data_nsa'!C13 -> 531105 | D10: ='US Raw Data_nsa'!D13 -> 479183 | E10: ='US Raw Data_nsa'!E13 -> 88527 | F10: =D10-E10 -> 390656 | G10: ='US Raw Data_nsa'!F13 -> 5685938 | H10: =F10-C10+E10+G9 -> 5721470 | I10: =G10-H10 -> -35532 | J10: =F10-C10+E10+J9 -> 5392636 | K10: =F10-C10+E10+I10+K9 -> 5685938 | M10: =400*F10/(4*B10) -> 15.204965 | N10: =400*C10/(4*B10) -> 20.671468 | O10: =100*G10/(4*B10) -> 55.326482 | P10: =100*G9/(4*B10) -> 56.177445 | Q10: =400*E10/(4*B10)*(1/(P10/100)) -> 6.1334481 | R10: =400*I10/(4*B10) -> -1.3829631 | S10: =(1/4)*(M10-N10+R10)+(1+(Q10/400))*P10 -> 55.326482 | T10: =(1/4)*(M10-N10+R10)+(1+(Q10/400))*U9 -> 58.12402 | U10: =T10*(B9/B10) -> 55.400822
A11: ='US Raw Data_nsa'!A14 -> 2000-Q3 | B11: ='US Raw Data_nsa'!B14 -> 2577927 | C11: ='US Raw Data_nsa'!C14 -> 522953 | D11: ='US Raw Data_nsa'!D14 -> 472437 | E11: ='US Raw Data_nsa'!E14 -> 88219 | F11: =D11-E11 -> 384218 | G11: ='US Raw Data_nsa'!F14 -> 5674179 | H11: =F11-C11+E11+G10 -> 5635422 | I11: =G11-H11 -> 38757 | J11: =F11-C11+E11+J10 -> 5342120 | K11: =F11-C11+E11+I11+K10 -> 5674179 | M11: =400*F11/(4*B11) -> 14.904146 | N11: =400*C11/(4*B11) -> 20.285796 | O11: =100*G11/(4*B11) -> 55.026568 | P11: =100*G10/(4*B11) -> 55.140603 | Q11: =400*E11/(4*B11)*(1/(P11/100)) -> 6.2061176 | R11: =400*I11/(4*B11) -> 1.5034173 | S11: =(1/4)*(M11-N11+R11)+(1+(Q11/400))*P11 -> 55.026568 | T11: =(1/4)*(M11-N11+R11)+(1+(Q11/400))*U10 -> 55.290824 | U11: =T11*(B10/B11) -> 55.105064
A12: ='US Raw Data_nsa'!A15 -> 2000-Q4 | B12: ='US Raw Data_nsa'!B15 -> 2655636 | C12: ='US Raw Data_nsa'!C15 -> 514356 | D12: ='US Raw Data_nsa'!D15 -> 488430 | E12: ='US Raw Data_nsa'!E15 -> 88276 | F12: =D12-E12 -> 400154 | G12: ='US Raw Data_nsa'!F15 -> 5662216 | H12: =F12-C12+E12+G11 -> 5648253 | I12: =G12-H12 -> 13963 | J12: =F12-C12+E12+J11 -> 5316194 | K12: =F12-C12+E12+I12+K11 -> 5662216 | M12: =400*F12/(4*B12) -> 15.068104 | N12: =400*C12/(4*B12) -> 19.368468 | O12: =100*G12/(4*B12) -> 53.303766 | P12: =100*G11/(4*B12) -> 53.416385 | Q12: =400*E12/(4*B12)*(1/(P12/100)) -> 6.2229972 | R12: =400*I12/(4*B12) -> 0.52578742 | S12: =(1/4)*(M12-N12+R12)+(1+(Q12/400))*P12 -> 53.303766 | T12: =(1/4)*(M12-N12+R12)+(1+(Q12/400))*U11 -> 55.018717 | U12: =T12*(B11/B12) -> 53.408764
A13: ='US Raw Data_nsa'!A16 -> 2001-Q1 | B13: ='US Raw Data_nsa'!B16 -> 2562488 | C13: ='US Raw Data_nsa'!C16 -> 511352 | D13: ='US Raw Data_nsa'!D16 -> 497170 | E13: ='US Raw Data_nsa'!E16 -> 86370 | F13: =D13-E13 -> 410800 | G13: ='US Raw Data_nsa'!F16 -> 5773740 | H13: =F13-C13+E13+G12 -> 5648034 | I13: =G13-H13 -> 125706 | J13: =F13-C13+E13+J12 -> 5302012 | K13: =F13-C13+E13+I13+K12 -> 5773740 | M13: =400*F13/(4*B13) -> 16.031295 | N13: =400*C13/(4*B13) -> 19.955293 | O13: =100*G13/(4*B13) -> 56.329435 | P13: =100*G12/(4*B13) -> 55.24139 | Q13: =400*E13/(4*B13)*(1/(P13/100)) -> 6.1014981 | R13: =400*I13/(4*B13) -> 4.905623 | S13: =(1/4)*(M13-N13+R13)+(1+(Q13/400))*P13 -> 56.329435 | T13: =(1/4)*(M13-N13+R13)+(1+(Q13/400))*U12 -> 54.468854 | U13: =T13*(B12/B13) -> 56.44883
A14: ='US Raw Data_nsa'!A17 -> 2001-Q2 | B14: ='US Raw Data_nsa'!B17 -> 2656407 | C14: ='US Raw Data_nsa'!C17 -> 537564 | D14: ='US Raw Data_nsa'!D17 -> 503150 | E14: ='US Raw Data_nsa'!E17 -> 83694 | F14: =D14-E14 -> 419456 | G14: ='US Raw Data_nsa'!F17 -> 5726815 | H14: =F14-C14+E14+G13 -> 5739326 | I14: =G14-H14 -> -12511 | J14: =F14-C14+E14+J13 -> 5267598 | K14: =F14-C14+E14+I14+K13 -> 5726815 | M14: =400*F14/(4*B14) -> 15.790351 | N14: =400*C14/(4*B14) -> 20.236507 | O14: =100*G14/(4*B14) -> 53.89625 | P14: =100*G13/(4*B14) -> 54.337871 | Q14: =400*E14/(4*B14)*(1/(P14/100)) -> 5.7982521 | R14: =400*I14/(4*B14) -> -0.47097452 | S14: =(1/4)*(M14-N14+R14)+(1+(Q14/400))*P14 -> 53.89625 | T14: =(1/4)*(M14-N14+R14)+(1+(Q14/400))*U13 -> 56.037808 | U14: =T14*(B13/B14) -> 54.056555
A15: ='US Raw Data_nsa'!A18 -> 2001-Q3 | B15: ='US Raw Data_nsa'!B18 -> 2651366 | C15: ='US Raw Data_nsa'!C18 -> 485197 | D15: ='US Raw Data_nsa'!D18 -> 501435 | E15: ='US Raw Data_nsa'!E18 -> 81707 | F15: =D15-E15 -> 419728 | G15: ='US Raw Data_nsa'!F18 -> 5807464 | H15: =F15-C15+E15+G14 -> 5743053 | I15: =G15-H15 -> 64411 | J15: =F15-C15+E15+J14 -> 5283836 | K15: =F15-C15+E15+I15+K14 -> 5807464 | M15: =400*F15/(4*B15) -> 15.830632 | N15: =400*C15/(4*B15) -> 18.299888 | O15: =100*G15/(4*B15) -> 54.759169 | P15: =100*G14/(4*B15) -> 53.998722 | Q15: =400*E15/(4*B15)*(1/(P15/100)) -> 5.7069767 | R15: =400*I15/(4*B15) -> 2.4293515 | S15: =(1/4)*(M15-N15+R15)+(1+(Q15/400))*P15 -> 54.759169 | T15: =(1/4)*(M15-N15+R15)+(1+(Q15/400))*U14 -> 54.817828 | U15: =T15*(B14/B15) -> 54.922052
A16: ='US Raw Data_nsa'!A19 -> 2001-Q4 | B16: ='US Raw Data_nsa'!B19 -> 2711715 | C16: ='US Raw Data_nsa'!C19 -> 498255 | D16: ='US Raw Data_nsa'!D19 -> 515573 | E16: ='US Raw Data_nsa'!E19 -> 79455 | F16: =D16-E16 -> 436118 | G16: ='US Raw Data_nsa'!F19 -> 5943439 | H16: =F16-C16+E16+G15 -> 5824782 | I16: =G16-H16 -> 118657 | J16: =F16-C16+E16+J15 -> 5301154 | K16: =F16-C16+E16+I16+K15 -> 5943439 | M16: =400*F16/(4*B16) -> 16.082737 | N16: =400*C16/(4*B16) -> 18.374165 | O16: =100*G16/(4*B16) -> 54.794097 | P16: =100*G15/(4*B16) -> 53.540508 | Q16: =400*E16/(4*B16)*(1/(P16/100)) -> 5.4726125 | R16: =400*I16/(4*B16) -> 4.3757179 | S16: =(1/4)*(M16-N16+R16)+(1+(Q16/400))*P16 -> 54.794097 | T16: =(1/4)*(M16-N16+R16)+(1+(Q16/400))*U15 -> 56.194542 | U16: =T16*(B15/B16) -> 54.943937
... A112: ='US Raw Data_nsa'!A115 -> 2025-Q4 | B112: ='US Raw Data_nsa'!B115 -> 7971751 | C112: ='US Raw Data_nsa'!C115 -> 1501013 | D112: ='US Raw Data_nsa'!D115 -> 1892982 | E112: ='US Raw Data_nsa'!E115 -> 306874 | F112: =D112-E112 -> 1586108 | G112: ='US Raw Data_nsa'!F115 -> 38514009 | H112: =F112-C112+E112+G111 -> 38029522 | I112: =G112-H112 -> 484487.4 | J112: =F112-C112+E112+J111 -> 29954491 | K112: =F112-C112+E112+I112+K111 -> 38514009 | M112: =400*F112/(4*B112) -> 19.896607 | N112: =400*C112/(4*B112) -> 18.829151 | O112: =100*G112/(4*B112) -> 120.78278 | P112: =100*G111/(4*B112) -> 118.03415 | Q112: =400*E112/(4*B112)*(1/(P112/100)) -> 3.2613598 | R112: =400*I112/(4*B112) -> 6.0775532 | S112: =(1/4)*(M112-N112+R112)+(1+(Q112/400))*P112 -> 120.78278 | T112: =(1/4)*(M112-N112+R112)+(1+(Q112/400))*U111 -> 123.37637 | U112: =T112*(B111/B112) -> 120.66682

Sheet UScalc
A1: Quarter | B1: GDPN | C1: TAX | D1: GEXP+INTEXP | E1: INTEXP | F1: GEXP | G1: DEBT | H1: DEBTCheck1 | I1: RESID | J1: DEBTCheck2 | K1: DEBTCheck3 | M1: GEXPSHR | N1: TAXSHR | O1: DEBTG | P1: DEBTGL | Q1: Ieff | R1: FFLOWSHR | S1: DEBTcheck Static | T1: DEBTcheck Dynamic | AF1: Is DEBTG end of period?
A2: ='US Raw Data'!A5 -> 1998-Q2 | B2: ='US Raw Data'!B5 -> 8969.699 | C2: ='US Raw Data'!C5 -> 1771.548 | D2: ='US Raw Data'!D5 -> 1781.911 | E2: ='US Raw Data'!E5 -> 367.648 | F2: =D2-E2 -> 1414.263 | G2: ='US Raw Data'!F5*(B2*4/100) -> 22191.739 | M2: =400*F2/(4*B2) -> 15.767118 | N2: =400*C2/(4*B2) -> 19.750362 | O2: =100*G2/(4*B2) -> 61.85196 | P2: NaN | Q2: NaN | R2: NaN | T2: GDP(t-1) | U2: GDP(t) | AF2: Are expenditures includig or excluding interest rate component?
A3: ='US Raw Data'!A6 -> 1998-Q3 | B3: ='US Raw Data'!B6 -> 9121.097 | C3: ='US Raw Data'!C6 -> 1808.447 | D3: ='US Raw Data'!D6 -> 1788.538 | E3: ='US Raw Data'!E6 -> 366.204 | F3: =D3-E3 -> 1422.334 | G3: ='US Raw Data'!F6*(B3*4/100) -> 22104.771 | H3: =F3-C3+E3+G2 -> 22171.83 | I3: =G3-H3 -> -67.058932 | J3: =F3-C3+E3+G2 -> 22171.83 | K3: =F3-C3+E3+I3+G2 -> 22104.771 | M3: =400*F3/(4*B3) -> 15.593892 | N3: =400*C3/(4*B3) -> 19.827078 | O3: =100*G3/(4*B3) -> 60.58693 | P3: =100*G2/(4*B3) -> 60.8253 | Q3: =400*E3/(4*B3)*(1/(P3/100)) -> 6.6007266 | R3: =400*I3/(4*B3) -> -0.73520687 | S3: =(1/4)*(M3-N3+R3)+(1+(Q3/400))*P3 -> 60.58693 | T3: =(1/4)*(M3-N3+R3)+(1+(Q3/400))*P3 -> 60.58693
A4: ='US Raw Data'!A7 -> 1998-Q4 | B4: ='US Raw Data'!B7 -> 9293.991 | C4: ='US Raw Data'!C7 -> 1835.085 | D4: ='US Raw Data'!D7 -> 1814.518 | E4: ='US Raw Data'!E7 -> 360.088 | F4: =D4-E4 -> 1454.43 | G4: ='US Raw Data'!F7*(B4*4/100) -> 22456.87 | H4: =F4-C4+E4+G3 -> 22084.204 | I4: =G4-H4 -> 372.66608 | J4: =F4-C4+E4+J3 -> 22151.263 | K4: =F4-C4+E4+I4+K3 -> 22456.87 | M4: =400*F4/(4*B4) -> 15.649144 | N4: =400*C4/(4*B4) -> 19.744854 | O4: =100*G4/(4*B4) -> 60.40696 | P4: =100*G3/(4*B4) -> 59.459845 | Q4: =400*E4/(4*B4)*(1/(P4/100)) -> 6.5160233 | R4: =400*I4/(4*B4) -> 4.009753 | S4: =(1/4)*(M4-N4+R4)+(1+(Q4/400))*P4 -> 60.40696 | T4: =(1/4)*(M4-N4+R4)+(1+(Q4/400))*T3 -> 61.552405 | U4: =T4*(B3/B4) -> 60.40736
A5: ='US Raw Data'!A8 -> 1999-Q1 | B5: ='US Raw Data'!B8 -> 9411.682 | C5: ='US Raw Data'!C8 -> 1860.002 | D5: ='US Raw Data'!D8 -> 1811.988 | E5: ='US Raw Data'!E8 -> 352.596 | F5: =D5-E5 -> 1459.392 | G5: ='US Raw Data'!F8*(B5*4/100) -> 22606.461 | H5: =F5-C5+E5+G4 -> 22408.856 | I5: =G5-H5 -> 197.60541 | J5: =F5-C5+E5+J4 -> 22103.249 | K5: =F5-C5+E5+I5+K4 -> 22606.461 | M5: =400*F5/(4*B5) -> 15.506176 | N5: =400*C5/(4*B5) -> 19.762695 | O5: =100*G5/(4*B5) -> 60.04894 | P5: =100*G4/(4*B5) -> 59.651584 | Q5: =400*E5/(4*B5)*(1/(P5/100)) -> 6.2804123 | R5: =400*I5/(4*B5) -> 2.0995759 | S5: =(1/4)*(M5-N5+R5)+(1+(Q5/400))*P5 -> 60.04894 | T5: =(1/4)*(M5-N5+R5)+(1+(Q5/400))*U4 -> 60.816582 | U5: =T5*(B4/B5) -> 60.056084
A6: ='US Raw Data'!A9 -> 1999-Q2 | B6: ='US Raw Data'!B9 -> 9526.21 | C6: ='US Raw Data'!C9 -> 1885.184 | D6: ='US Raw Data'!D9 -> 1816.961 | E6: ='US Raw Data'!E9 -> 352.141 | F6: =D6-E6 -> 1464.82 | G6: ='US Raw Data'!F9*(B6*4/100) -> 22555.12 | H6: =F6-C6+E6+G5 -> 22538.238 | I6: =G6-H6 -> 16.881667 | J6: =F6-C6+E6+J5 -> 22035.026 | K6: =F6-C6+E6+I6+K5 -> 22555.12 | M6: =400*F6/(4*B6) -> 15.376734 | N6: =400*C6/(4*B6) -> 19.789444 | O6: =100*G6/(4*B6) -> 59.19227 | P6: =100*G5/(4*B6) -> 59.327007 | Q6: =400*E6/(4*B6)*(1/(P6/100)) -> 6.2308027 | R6: =400*I6/(4*B6) -> 0.17721284 | S6: =(1/4)*(M6-N6+R6)+(1+(Q6/400))*P6 -> 59.19227 | T6: =(1/4)*(M6-N6+R6)+(1+(Q6/400))*U5 -> 59.932704 | U6: =T6*(B5/B6) -> 59.212168
A7: ='US Raw Data'!A10 -> 1999-Q3 | B7: ='US Raw Data'!B10 -> 9686.626 | C7: ='US Raw Data'!C10 -> 1914.862 | D7: ='US Raw Data'!D10 -> 1843.205 | E7: ='US Raw Data'!E10 -> 351.073 | F7: =D7-E7 -> 1492.132 | G7: ='US Raw Data'!F10*(B7*4/100) -> 22625.083 | H7: =F7-C7+E7+G6 -> 22483.463 | I7: =G7-H7 -> 141.62057 | J7: =F7-C7+E7+J6 -> 21963.369 | K7: =F7-C7+E7+I7+K6 -> 22625.083 | M7: =400*F7/(4*B7) -> 15.404043 | N7: =400*C7/(4*B7) -> 19.768101 | O7: =100*G7/(4*B7) -> 58.39258 | P7: =100*G6/(4*B7) -> 58.212013 | Q7: =400*E7/(4*B7)*(1/(P7/100)) -> 6.2260454 | R7: =400*I7/(4*B7) -> 1.4620217 | S7: =(1/4)*(M7-N7+R7)+(1+(Q7/400))*P7 -> 58.39258 | T7: =(1/4)*(M7-N7+R7)+(1+(Q7/400))*U6 -> 59.408303 | U7: =T7*(B6/B7) -> 58.424468
A8: ='US Raw Data'!A11 -> 1999-Q4 | B8: ='US Raw Data'!B11 -> 9900.169 | C8: ='US Raw Data'!C11 -> 1963.756 | D8: ='US Raw Data'!D11 -> 1875.154 | E8: ='US Raw Data'!E11 -> 352.925 | F8: =D8-E8 -> 1522.229 | G8: ='US Raw Data'!F11*(B8*4/100) -> 23104.365 | H8: =F8-C8+E8+G7 -> 22536.481 | I8: =G8-H8 -> 567.88362 | J8: =F8-C8+E8+J7 -> 21874.767 | K8: =F8-C8+E8+I8+K7 -> 23104.365 | M8: =400*F8/(4*B8) -> 15.375788 | N8: =400*C8/(4*B8) -> 19.835581 | O8: =100*G8/(4*B8) -> 58.34336 | P8: =100*G7/(4*B8) -> 57.133074 | Q8: =400*E8/(4*B8)*(1/(P8/100)) -> 6.239535 | R8: =400*I8/(4*B8) -> 5.7361002 | S8: =(1/4)*(M8-N8+R8)+(1+(Q8/400))*P8 -> 58.34336 | T8: =(1/4)*(M8-N8+R8)+(1+(Q8/400))*U7 -> 59.654899 | U8: =T8*(B7/B8) -> 58.368165
A9: ='US Raw Data'!A12 -> 2000-Q1 | B9: ='US Raw Data'!B12 -> 10002.179 | C9: ='US Raw Data'!C12 -> 2041.764 | D9: ='US Raw Data'!D12 -> 1866.308 | E9: ='US Raw Data'!E12 -> 354.822 | F9: =D9-E9 -> 1511.486 | G9: ='US Raw Data'!F12*(B9*4/100) -> 23093.567 | H9: =F9-C9+E9+G8 -> 22928.909 | I9: =G9-H9 -> 164.65803 | J9: =F9-C9+E9+J8 -> 21699.311 | K9: =F9-C9+E9+I9+K8 -> 23093.567 | M9: =400*F9/(4*B9) -> 15.111567 | N9: =400*C9/(4*B9) -> 20.413192 | O9: =100*G9/(4*B9) -> 57.72134 | P9: =100*G8/(4*B9) -> 57.748329 | Q9: =400*E9/(4*B9)*(1/(P9/100)) -> 6.1429431 | R9: =400*I9/(4*B9) -> 1.6462216 | S9: =(1/4)*(M9-N9+R9)+(1+(Q9/400))*P9 -> 57.72134 | T9: =(1/4)*(M9-N9+R9)+(1+(Q9/400))*U8 -> 58.350695 | U9: =T9*(B8/B9) -> 57.755589
A10: ='US Raw Data'!A13 -> 2000-Q2 | B10: ='US Raw Data'!B13 -> 10247.72 | C10: ='US Raw Data'!C13 -> 2056.279 | D10: ='US Raw Data'!D13 -> 1908.645 | E10: ='US Raw Data'!E13 -> 354.109 | F10: =D10-E10 -> 1554.536 | G10: ='US Raw Data'!F13*(B10*4/100) -> 22743.753 | H10: =F10-C10+E10+G9 -> 22945.933 | I10: =G10-H10 -> -202.18012 | J10: =F10-C10+E10+J9 -> 21551.677 | K10: =F10-C10+E10+I10+K9 -> 22743.753 | M10: =400*F10/(4*B10) -> 15.169579 | N10: =400*C10/(4*B10) -> 20.065722 | O10: =100*G10/(4*B10) -> 55.48491 | P10: =100*G9/(4*B10) -> 56.338305 | Q10: =400*E10/(4*B10)*(1/(P10/100)) -> 6.1334657 | R10: =400*I10/(4*B10) -> -1.9729278 | S10: =(1/4)*(M10-N10+R10)+(1+(Q10/400))*P10 -> 55.48491 | T10: =(1/4)*(M10-N10+R10)+(1+(Q10/400))*U9 -> 56.923926 | U10: =T10*(B9/B10) -> 55.559998
A11: ='US Raw Data'!A14 -> 2000-Q3 | B11: ='US Raw Data'!B14 -> 10318.165 | C11: ='US Raw Data'!C14 -> 2076.268 | D11: ='US Raw Data'!D14 -> 1918.617 | E11: ='US Raw Data'!E14 -> 352.877 | F11: =D11-E11 -> 1565.74 | G11: ='US Raw Data'!F14*(B11*4/100) -> 22696.715 | H11: =F11-C11+E11+G10 -> 22586.102 | I11: =G11-H11 -> 110.61297 | J11: =F11-C11+E11+J10 -> 21394.026 | K11: =F11-C11+E11+I11+K10 -> 22696.715 | M11: =400*F11/(4*B11) -> 15.174597 | N11: =400*C11/(4*B11) -> 20.122454 | O11: =100*G11/(4*B11) -> 54.99213 | P11: =100*G10/(4*B11) -> 55.106099 | Q11: =400*E11/(4*B11)*(1/(P11/100)) -> 6.206135 | R11: =400*I11/(4*B11) -> 1.0720217 | S11: =(1/4)*(M11-N11+R11)+(1+(Q11/400))*P11 -> 54.99213 | T11: =(1/4)*(M11-N11+R11)+(1+(Q11/400))*U10 -> 55.453071 | U11: =T11*(B10/B11) -> 55.074477
A12: ='US Raw Data'!A15 -> 2000-Q4 | B12: ='US Raw Data'!B15 -> 10435.744 | C12: ='US Raw Data'!C15 -> 2096.796 | D12: ='US Raw Data'!D15 -> 1938.796 | E12: ='US Raw Data'!E15 -> 353.105 | F12: =D12-E12 -> 1585.691 | G12: ='US Raw Data'!F15*(B12*4/100) -> 22648.862 | H12: =F12-C12+E12+G11 -> 22538.715 | I12: =G12-H12 -> 110.14733 | J12: =F12-C12+E12+J11 -> 21236.026 | K12: =F12-C12+E12+I12+K11 -> 22648.862 | M12: =400*F12/(4*B12) -> 15.194805 | N12: =400*C12/(4*B12) -> 20.092444 | O12: =100*G12/(4*B12) -> 54.2579 | P12: =100*G11/(4*B12) -> 54.372536 | Q12: =400*E12/(4*B12)*(1/(P12/100)) -> 6.2230151 | R12: =400*I12/(4*B12) -> 1.0554814 | S12: =(1/4)*(M12-N12+R12)+(1+(Q12/400))*P12 -> 54.2579 | T12: =(1/4)*(M12-N12+R12)+(1+(Q12/400))*U11 -> 54.970761 | U12: =T12*(B11/B12) -> 54.351409
A13: ='US Raw Data'!A16 -> 2001-Q1 | B13: ='US Raw Data'!B16 -> 10470.231 | C13: ='US Raw Data'!C16 -> 2111.058 | D13: ='US Raw Data'!D16 -> 1982.626 | E13: ='US Raw Data'!E16 -> 345.479 | F13: =D13-E13 -> 1637.147 | G13: ='US Raw Data'!F16*(B13*4/100) -> 23094.959 | H13: =F13-C13+E13+G12 -> 22520.43 | I13: =G13-H13 -> 574.52895 | J13: =F13-C13+E13+J12 -> 21107.594 | K13: =F13-C13+E13+I13+K12 -> 23094.959 | M13: =400*F13/(4*B13) -> 15.636207 | N13: =400*C13/(4*B13) -> 20.162478 | O13: =100*G13/(4*B13) -> 55.14434 | P13: =100*G12/(4*B13) -> 54.079185 | Q13: =400*E13/(4*B13)*(1/(P13/100)) -> 6.1014809 | R13: =400*I13/(4*B13) -> 5.4872615 | S13: =(1/4)*(M13-N13+R13)+(1+(Q13/400))*P13 -> 55.14434 | T13: =(1/4)*(M13-N13+R13)+(1+(Q13/400))*U12 -> 55.420716 | U13: =T13*(B12/B13) -> 55.238171
A14: ='US Raw Data'!A17 -> 2001-Q2 | B14: ='US Raw Data'!B17 -> 10599 | C14: ='US Raw Data'!C17 -> 2098.359 | D14: ='US Raw Data'!D17 -> 2003.581 | E14: ='US Raw Data'!E17 -> 334.776 | F14: =D14-E14 -> 1668.805 | G14: ='US Raw Data'!F17*(B14*4/100) -> 22907.258 | H14: =F14-C14+E14+G13 -> 23000.181 | I14: =G14-H14 -> -92.922792 | J14: =F14-C14+E14+J13 -> 21012.816 | K14: =F14-C14+E14+I14+K13 -> 22907.258 | M14: =400*F14/(4*B14) -> 15.744929 | N14: =400*C14/(4*B14) -> 19.797707 | O14: =100*G14/(4*B14) -> 54.03165 | P14: =100*G13/(4*B14) -> 54.474382 | Q14: =400*E14/(4*B14)*(1/(P14/100)) -> 5.7982523 | R14: =400*I14/(4*B14) -> -0.87671282 | S14: =(1/4)*(M14-N14+R14)+(1+(Q14/400))*P14 -> 54.03165 | T14: =(1/4)*(M14-N14+R14)+(1+(Q14/400))*U13 -> 54.80651 | U14: =T14*(B13/B14) -> 54.140657
A15: ='US Raw Data'!A18 -> 2001-Q3 | B15: ='US Raw Data'!B18 -> 10598.02 | C15: ='US Raw Data'!C18 -> 1907.679 | D15: ='US Raw Data'!D18 -> 2037.703 | E15: ='US Raw Data'!E18 -> 326.826 | F15: =D15-E15 -> 1710.877 | G15: ='US Raw Data'!F18*(B15*4/100) -> 23229.855 | H15: =F15-C15+E15+G14 -> 23037.282 | I15: =G15-H15 -> 192.57281 | J15: =F15-C15+E15+J14 -> 21142.84 | K15: =F15-C15+E15+I15+K14 -> 23229.855 | M15: =400*F15/(4*B15) -> 16.143365 | N15: =400*C15/(4*B15) -> 18.000334 | O15: =100*G15/(4*B15) -> 54.79763 | P15: =100*G14/(4*B15) -> 54.036646 | Q15: =400*E15/(4*B15)*(1/(P15/100)) -> 5.7069422 | R15: =400*I15/(4*B15) -> 1.8170641 | S15: =(1/4)*(M15-N15+R15)+(1+(Q15/400))*P15 -> 54.79763 | T15: =(1/4)*(M15-N15+R15)+(1+(Q15/400))*U14 -> 54.903124 | U15: =T15*(B14/B15) -> 54.908201
A16: ='US Raw Data'!A19 -> 2001-Q4 | B16: ='US Raw Data'!B19 -> 10660.465 | C16: ='US Raw Data'!C19 -> 2012.375 | D16: ='US Raw Data'!D19 -> 2045.404 | E16: ='US Raw Data'!E19 -> 317.821 | F16: =D16-E16 -> 1727.583 | G16: ='US Raw Data'!F19*(B16*4/100) -> 23773.758 | H16: =F16-C16+E16+G15 -> 23262.884 | I16: =G16-H16 -> 510.87387 | J16: =F16-C16+E16+J15 -> 21175.869 | K16: =F16-C16+E16+I16+K15 -> 23773.758 | M16: =400*F16/(4*B16) -> 16.205513 | N16: =400*C16/(4*B16) -> 18.876991 | O16: =100*G16/(4*B16) -> 55.75216 | P16: =100*G15/(4*B16) -> 54.476646 | Q16: =400*E16/(4*B16)*(1/(P16/100)) -> 5.4726299 | R16: =400*I16/(4*B16) -> 4.7922287 | S16: =(1/4)*(M16-N16+R16)+(1+(Q16/400))*P16 -> 55.75216 | T16: =(1/4)*(M16-N16+R16)+(1+(Q16/400))*U15 -> 56.18962 | U16: =T16*(B15/B16) -> 55.860482
... A112: ='US Raw Data'!A115 -> 2025-Q4 | B112: ='US Raw Data'!B115 -> 31422.526 | C112: ='US Raw Data'!C115 -> 5898.479 | D112: ='US Raw Data'!D115 -> 7583.663 | E112: ='US Raw Data'!E115 -> 1227.495 | F112: =D112-E112 -> 6356.168 | G112: ='US Raw Data'!F115*(B112*4/100) -> 154056.04 | H112: =F112-C112+E112+G111 -> 152235.4 | I112: =G112-H112 -> 1820.6378 | J112: =F112-C112+E112+J111 -> 120026.83 | K112: =F112-C112+E112+I112+K111 -> 154056.04 | M112: =400*F112/(4*B112) -> 20.228062 | N112: =400*C112/(4*B112) -> 18.771499 | O112: =100*G112/(4*B112) -> 122.56815 | P112: =100*G111/(4*B112) -> 119.77889 | Q112: =400*E112/(4*B112)*(1/(P112/100)) -> 3.2613571 | R112: =400*I112/(4*B112) -> 5.794053 | S112: =(1/4)*(M112-N112+R112)+(1+(Q112/400))*P112 -> 122.56815 | T112: =(1/4)*(M112-N112+R112)+(1+(Q112/400))*U111 -> 124.09977 | U112: =T112*(B111/B112) -> 122.8182

Sheet UScalc_LagY
A1: Quarter | B1: GDPN | C1: TAX | D1: GEXP+INTEXP | E1: INTEXP | F1: GEXP | G1: DEBT | H1: DEBTCheck1 | I1: RESID | J1: DEBTCheck2 | K1: DEBTCheck3 | M1: GEXPSHR | N1: TAXSHR | O1: DEBTG | P1: DEBTGLag | Q1: Ieff | R1: FFLOWSHR | S1: DEBTcheck Static | U1: DEBTcheck Dynamic | AG1: Is DEBTG end of period?
A2: ='US Raw Data'!A5 -> 1998-Q2 | B2: ='US Raw Data'!B5 -> 8969.699 | C2: ='US Raw Data'!C5 -> 1771.548 | D2: ='US Raw Data'!D5 -> 1781.911 | E2: ='US Raw Data'!E5 -> 367.648 | F2: =D2-E2 -> 1414.263 | G2: ='US Raw Data'!F5*(B2*4/100) -> 22191.739 | O2: =100*G2/(4*B2) -> 61.85196 | P2: NaN | Q2: NaN | R2: NaN | S2: GDP(t-1) | T2: GDP(t) | U2: GDP(t-1) | V2: GDP(t) | AG2: Are expenditures includig or excluding interest rate component?
A3: ='US Raw Data'!A6 -> 1998-Q3 | B3: ='US Raw Data'!B6 -> 9121.097 | C3: ='US Raw Data'!C6 -> 1808.447 | D3: ='US Raw Data'!D6 -> 1788.538 | E3: ='US Raw Data'!E6 -> 366.204 | F3: =D3-E3 -> 1422.334 | G3: ='US Raw Data'!F6*(B3*4/100) -> 22104.771 | H3: =F3-C3+E3+G2 -> 22171.83 | I3: =G3-H3 -> -67.058932 | J3: =F3-C3+E3+G2 -> 22171.83 | K3: =F3-C3+E3+I3+G2 -> 22104.771 | M3: =400*F3/(4*B2) -> 15.857098 | N3: =400*C3/(4*B2) -> 20.161736 | O3: =100*G3/(4*B3) -> 60.58693 | P3: =100*G3/(4*B2) -> 61.609566 | Q3: =400*E3/(4*B2)*(1/(O2/100)) -> 6.6007266 | R3: =400*I3/(4*B2) -> -0.7476163 | S3: =((1/4)*(M3-N3+R3)+(1+(Q3/400))*O2) -> 61.609566 | T3: =((1/4)*(M3-N3+R3)+(1+(Q3/400))*O2)*(B2/B3) -> 60.58693 | U3: =(1/4)*(M3-N3+R3)+(1+(Q3/400))*O2 -> 61.609566 | V3: =U3*(B2/B3) -> 60.58693
A4: ='US Raw Data'!A7 -> 1998-Q4 | B4: ='US Raw Data'!B7 -> 9293.991 | C4: ='US Raw Data'!C7 -> 1835.085 | D4: ='US Raw Data'!D7 -> 1814.518 | E4: ='US Raw Data'!E7 -> 360.088 | F4: =D4-E4 -> 1454.43 | G4: ='US Raw Data'!F7*(B4*4/100) -> 22456.87 | H4: =F4-C4+E4+G3 -> 22084.204 | I4: =G4-H4 -> 372.66608 | J4: =F4-C4+E4+J3 -> 22151.263 | K4: =F4-C4+E4+I4+K3 -> 22456.87 | M4: =400*F4/(4*B3) -> 15.945779 | N4: =400*C4/(4*B3) -> 20.119126 | O4: =100*G4/(4*B4) -> 60.40696 | P4: =100*G4/(4*B3) -> 61.551998 | Q4: =400*E4/(4*B3)*(1/(O3/100)) -> 6.5160233 | R4: =400*I4/(4*B3) -> 4.0857595 | S4: =((1/4)*(M4-N4+R4)+(1+(Q4/400))*O3) -> 61.551998 | T4: =((1/4)*(M4-N4+R4)+(1+(Q4/400))*O3)*(B3/B4) -> 60.40696 | U4: =(1/4)*(M4-N4+R4)+(1+(Q4/400))*V3 -> 61.551998 | V4: =U4*(B3/B4) -> 60.40696
A5: ='US Raw Data'!A8 -> 1999-Q1 | B5: ='US Raw Data'!B8 -> 9411.682 | C5: ='US Raw Data'!C8 -> 1860.002 | D5: ='US Raw Data'!D8 -> 1811.988 | E5: ='US Raw Data'!E8 -> 352.596 | F5: =D5-E5 -> 1459.392 | G5: ='US Raw Data'!F8*(B5*4/100) -> 22606.461 | H5: =F5-C5+E5+G4 -> 22408.856 | I5: =G5-H5 -> 197.60541 | J5: =F5-C5+E5+J4 -> 22103.249 | K5: =F5-C5+E5+I5+K4 -> 22606.461 | M5: =400*F5/(4*B4) -> 15.702533 | N5: =400*C5/(4*B4) -> 20.012952 | O5: =100*G5/(4*B5) -> 60.04894 | P5: =100*G5/(4*B4) -> 60.809347 | Q5: =400*E5/(4*B4)*(1/(O4/100)) -> 6.2804123 | R5: =400*I5/(4*B4) -> 2.1261631 | S5: =((1/4)*(M5-N5+R5)+(1+(Q5/400))*O4) -> 60.809347 | T5: =((1/4)*(M5-N5+R5)+(1+(Q5/400))*O4)*(B4/B5) -> 60.04894 | U5: =(1/4)*(M5-N5+R5)+(1+(Q5/400))*V4 -> 60.809347 | V5: =U5*(B4/B5) -> 60.04894
A6: ='US Raw Data'!A9 -> 1999-Q2 | B6: ='US Raw Data'!B9 -> 9526.21 | C6: ='US Raw Data'!C9 -> 1885.184 | D6: ='US Raw Data'!D9 -> 1816.961 | E6: ='US Raw Data'!E9 -> 352.141 | F6: =D6-E6 -> 1464.82 | G6: ='US Raw Data'!F9*(B6*4/100) -> 22555.12 | H6: =F6-C6+E6+G5 -> 22538.238 | I6: =G6-H6 -> 16.881667 | J6: =F6-C6+E6+J5 -> 22035.026 | K6: =F6-C6+E6+I6+K5 -> 22555.12 | M6: =400*F6/(4*B5) -> 15.563849 | N6: =400*C6/(4*B5) -> 20.030256 | O6: =100*G6/(4*B6) -> 59.19227 | P6: =100*G6/(4*B5) -> 59.912563 | Q6: =400*E6/(4*B5)*(1/(O5/100)) -> 6.2308027 | R6: =400*I6/(4*B5) -> 0.17936929 | S6: =((1/4)*(M6-N6+R6)+(1+(Q6/400))*O5) -> 59.912563 | T6: =((1/4)*(M6-N6+R6)+(1+(Q6/400))*O5)*(B5/B6) -> 59.19227 | U6: =(1/4)*(M6-N6+R6)+(1+(Q6/400))*V5 -> 59.912563 | V6: =U6*(B5/B6) -> 59.19227
A7: ='US Raw Data'!A10 -> 1999-Q3 | B7: ='US Raw Data'!B10 -> 9686.626 | C7: ='US Raw Data'!C10 -> 1914.862 | D7: ='US Raw Data'!D10 -> 1843.205 | E7: ='US Raw Data'!E10 -> 351.073 | F7: =D7-E7 -> 1492.132 | G7: ='US Raw Data'!F10*(B7*4/100) -> 22625.083 | H7: =F7-C7+E7+G6 -> 22483.463 | I7: =G7-H7 -> 141.62057 | J7: =F7-C7+E7+J6 -> 21963.369 | K7: =F7-C7+E7+I7+K6 -> 22625.083 | M7: =400*F7/(4*B6) -> 15.663438 | N7: =400*C7/(4*B6) -> 20.100985 | O7: =100*G7/(4*B7) -> 58.39258 | P7: =100*G7/(4*B6) -> 59.375878 | Q7: =400*E7/(4*B6)*(1/(O6/100)) -> 6.2260454 | R7: =400*I7/(4*B6) -> 1.4866413 | S7: =((1/4)*(M7-N7+R7)+(1+(Q7/400))*O6) -> 59.375878 | T7: =((1/4)*(M7-N7+R7)+(1+(Q7/400))*O6)*(B6/B7) -> 58.39258 | U7: =(1/4)*(M7-N7+R7)+(1+(Q7/400))*V6 -> 59.375878 | V7: =U7*(B6/B7) -> 58.39258
A8: ='US Raw Data'!A11 -> 1999-Q4 | B8: ='US Raw Data'!B11 -> 9900.169 | C8: ='US Raw Data'!C11 -> 1963.756 | D8: ='US Raw Data'!D11 -> 1875.154 | E8: ='US Raw Data'!E11 -> 352.925 | F8: =D8-E8 -> 1522.229 | G8: ='US Raw Data'!F11*(B8*4/100) -> 23104.365 | H8: =F8-C8+E8+G7 -> 22536.481 | I8: =G8-H8 -> 567.88362 | J8: =F8-C8+E8+J7 -> 21874.767 | K8: =F8-C8+E8+I8+K7 -> 23104.365 | M8: =400*F8/(4*B7) -> 15.714749 | N8: =400*C8/(4*B7) -> 20.272859 | O8: =100*G8/(4*B8) -> 58.34336 | P8: =100*G8/(4*B7) -> 59.629547 | Q8: =400*E8/(4*B7)*(1/(O7/100)) -> 6.239535 | R8: =400*I8/(4*B7) -> 5.8625533 | S8: =((1/4)*(M8-N8+R8)+(1+(Q8/400))*O7) -> 59.629547 | T8: =((1/4)*(M8-N8+R8)+(1+(Q8/400))*O7)*(B7/B8) -> 58.34336 | U8: =(1/4)*(M8-N8+R8)+(1+(Q8/400))*V7 -> 59.629547 | V8: =U8*(B7/B8) -> 58.34336
A9: ='US Raw Data'!A12 -> 2000-Q1 | B9: ='US Raw Data'!B12 -> 10002.179 | C9: ='US Raw Data'!C12 -> 2041.764 | D9: ='US Raw Data'!D12 -> 1866.308 | E9: ='US Raw Data'!E12 -> 354.822 | F9: =D9-E9 -> 1511.486 | G9: ='US Raw Data'!F12*(B9*4/100) -> 23093.567 | H9: =F9-C9+E9+G8 -> 22928.909 | I9: =G9-H9 -> 164.65803 | J9: =F9-C9+E9+J8 -> 21699.311 | K9: =F9-C9+E9+I9+K8 -> 23093.567 | M9: =400*F9/(4*B8) -> 15.267275 | N9: =400*C9/(4*B8) -> 20.623527 | O9: =100*G9/(4*B9) -> 57.72134 | P9: =100*G9/(4*B8) -> 58.316093 | Q9: =400*E9/(4*B8)*(1/(O8/100)) -> 6.1429431 | R9: =400*I9/(4*B8) -> 1.663184 | S9: =((1/4)*(M9-N9+R9)+(1+(Q9/400))*O8) -> 58.316093 | T9: =((1/4)*(M9-N9+R9)+(1+(Q9/400))*O8)*(B8/B9) -> 57.72134 | U9: =(1/4)*(M9-N9+R9)+(1+(Q9/400))*V8 -> 58.316093 | V9: =U9*(B8/B9) -> 57.72134
A10: ='US Raw Data'!A13 -> 2000-Q2 | B10: ='US Raw Data'!B13 -> 10247.72 | C10: ='US Raw Data'!C13 -> 2056.279 | D10: ='US Raw Data'!D13 -> 1908.645 | E10: ='US Raw Data'!E13 -> 354.109 | F10: =D10-E10 -> 1554.536 | G10: ='US Raw Data'!F13*(B10*4/100) -> 22743.753 | H10: =F10-C10+E10+G9 -> 22945.933 | I10: =G10-H10 -> -202.18012 | J10: =F10-C10+E10+J9 -> 21551.677 | K10: =F10-C10+E10+I10+K9 -> 22743.753 | M10: =400*F10/(4*B9) -> 15.541973 | N10: =400*C10/(4*B9) -> 20.55831 | O10: =100*G10/(4*B10) -> 55.48491 | P10: =100*G10/(4*B9) -> 56.846995 | Q10: =400*E10/(4*B9)*(1/(O9/100)) -> 6.1334657 | R10: =400*I10/(4*B9) -> -2.0213607 | S10: =((1/4)*(M10-N10+R10)+(1+(Q10/400))*O9) -> 56.846995 | T10: =((1/4)*(M10-N10+R10)+(1+(Q10/400))*O9)*(B9/B10) -> 55.48491 | U10: =(1/4)*(M10-N10+R10)+(1+(Q10/400))*V9 -> 56.846995 | V10: =U10*(B9/B10) -> 55.48491
A11: ='US Raw Data'!A14 -> 2000-Q3 | B11: ='US Raw Data'!B14 -> 10318.165 | C11: ='US Raw Data'!C14 -> 2076.268 | D11: ='US Raw Data'!D14 -> 1918.617 | E11: ='US Raw Data'!E14 -> 352.877 | F11: =D11-E11 -> 1565.74 | G11: ='US Raw Data'!F14*(B11*4/100) -> 22696.715 | H11: =F11-C11+E11+G10 -> 22586.102 | I11: =G11-H11 -> 110.61297 | J11: =F11-C11+E11+J10 -> 21394.026 | K11: =F11-C11+E11+I11+K10 -> 22696.715 | M11: =400*F11/(4*B10) -> 15.278911 | N11: =400*C11/(4*B10) -> 20.26078 | O11: =100*G11/(4*B11) -> 54.99213 | P11: =100*G11/(4*B10) -> 55.370158 | Q11: =400*E11/(4*B10)*(1/(O10/100)) -> 6.206135 | R11: =400*I11/(4*B10) -> 1.079391 | S11: =((1/4)*(M11-N11+R11)+(1+(Q11/400))*O10) -> 55.370158 | T11: =((1/4)*(M11-N11+R11)+(1+(Q11/400))*O10)*(B10/B11) -> 54.99213 | U11: =(1/4)*(M11-N11+R11)+(1+(Q11/400))*V10 -> 55.370158 | V11: =U11*(B10/B11) -> 54.99213
A12: ='US Raw Data'!A15 -> 2000-Q4 | B12: ='US Raw Data'!B15 -> 10435.744 | C12: ='US Raw Data'!C15 -> 2096.796 | D12: ='US Raw Data'!D15 -> 1938.796 | E12: ='US Raw Data'!E15 -> 353.105 | F12: =D12-E12 -> 1585.691 | G12: ='US Raw Data'!F15*(B12*4/100) -> 22648.862 | H12: =F12-C12+E12+G11 -> 22538.715 | I12: =G12-H12 -> 110.14733 | J12: =F12-C12+E12+J11 -> 21236.026 | K12: =F12-C12+E12+I12+K11 -> 22648.862 | M12: =400*F12/(4*B11) -> 15.367955 | N12: =400*C12/(4*B11) -> 20.321404 | O12: =100*G12/(4*B12) -> 54.2579 | P12: =100*G12/(4*B11) -> 54.876187 | Q12: =400*E12/(4*B11)*(1/(O11/100)) -> 6.2230151 | R12: =400*I12/(4*B11) -> 1.0675089 | S12: =((1/4)*(M12-N12+R12)+(1+(Q12/400))*O11) -> 54.876187 | T12: =((1/4)*(M12-N12+R12)+(1+(Q12/400))*O11)*(B11/B12) -> 54.2579 | U12: =(1/4)*(M12-N12+R12)+(1+(Q12/400))*V11 -> 54.876187 | V12: =U12*(B11/B12) -> 54.2579
A13: ='US Raw Data'!A16 -> 2001-Q1 | B13: ='US Raw Data'!B16 -> 10470.231 | C13: ='US Raw Data'!C16 -> 2111.058 | D13: ='US Raw Data'!D16 -> 1982.626 | E13: ='US Raw Data'!E16 -> 345.479 | F13: =D13-E13 -> 1637.147 | G13: ='US Raw Data'!F16*(B13*4/100) -> 23094.959 | H13: =F13-C13+E13+G12 -> 22520.43 | I13: =G13-H13 -> 574.52895 | J13: =F13-C13+E13+J12 -> 21107.594 | K13: =F13-C13+E13+I13+K12 -> 23094.959 | M13: =400*F13/(4*B12) -> 15.68788 | N13: =400*C13/(4*B12) -> 20.229109 | O13: =100*G13/(4*B13) -> 55.14434 | P13: =100*G13/(4*B12) -> 55.326575 | Q13: =400*E13/(4*B12)*(1/(O12/100)) -> 6.1014809 | R13: =400*I13/(4*B12) -> 5.5053952 | S13: =((1/4)*(M13-N13+R13)+(1+(Q13/400))*O12) -> 55.326575 | T13: =((1/4)*(M13-N13+R13)+(1+(Q13/400))*O12)*(B12/B13) -> 55.14434 | U13: =(1/4)*(M13-N13+R13)+(1+(Q13/400))*V12 -> 55.326575 | V13: =U13*(B12/B13) -> 55.14434
A14: ='US Raw Data'!A17 -> 2001-Q2 | B14: ='US Raw Data'!B17 -> 10599 | C14: ='US Raw Data'!C17 -> 2098.359 | D14: ='US Raw Data'!D17 -> 2003.581 | E14: ='US Raw Data'!E17 -> 334.776 | F14: =D14-E14 -> 1668.805 | G14: ='US Raw Data'!F17*(B14*4/100) -> 22907.258 | H14: =F14-C14+E14+G13 -> 23000.181 | I14: =G14-H14 -> -92.922792 | J14: =F14-C14+E14+J13 -> 21012.816 | K14: =F14-C14+E14+I14+K13 -> 22907.258 | M14: =400*F14/(4*B13) -> 15.938569 | N14: =400*C14/(4*B13) -> 20.041191 | O14: =100*G14/(4*B14) -> 54.03165 | P14: =100*G14/(4*B13) -> 54.696163 | Q14: =400*E14/(4*B13)*(1/(O13/100)) -> 5.7982523 | R14: =400*I14/(4*B13) -> -0.88749514 | S14: =((1/4)*(M14-N14+R14)+(1+(Q14/400))*O13) -> 54.696163 | T14: =((1/4)*(M14-N14+R14)+(1+(Q14/400))*O13)*(B13/B14) -> 54.03165 | U14: =(1/4)*(M14-N14+R14)+(1+(Q14/400))*V13 -> 54.696163 | V14: =U14*(B13/B14) -> 54.03165
A15: ='US Raw Data'!A18 -> 2001-Q3 | B15: ='US Raw Data'!B18 -> 10598.02 | C15: ='US Raw Data'!C18 -> 1907.679 | D15: ='US Raw Data'!D18 -> 2037.703 | E15: ='US Raw Data'!E18 -> 326.826 | F15: =D15-E15 -> 1710.877 | G15: ='US Raw Data'!F18*(B15*4/100) -> 23229.855 | H15: =F15-C15+E15+G14 -> 23037.282 | I15: =G15-H15 -> 192.57281 | J15: =F15-C15+E15+J14 -> 21142.84 | K15: =F15-C15+E15+I15+K14 -> 23229.855 | M15: =400*F15/(4*B14) -> 16.141872 | N15: =400*C15/(4*B14) -> 17.99867 | O15: =100*G15/(4*B15) -> 54.79763 | P15: =100*G15/(4*B14) -> 54.792563 | Q15: =400*E15/(4*B14)*(1/(O14/100)) -> 5.7069422 | R15: =400*I15/(4*B14) -> 1.8168961 | S15: =((1/4)*(M15-N15+R15)+(1+(Q15/400))*O14) -> 54.792563 | T15: =((1/4)*(M15-N15+R15)+(1+(Q15/400))*O14)*(B14/B15) -> 54.79763 | U15: =(1/4)*(M15-N15+R15)+(1+(Q15/400))*V14 -> 54.792563 | V15: =U15*(B14/B15) -> 54.79763
... A112: ='US Raw Data'!A115 -> 2025-Q4 | B112: ='US Raw Data'!B115 -> 31422.526 | C112: ='US Raw Data'!C115 -> 5898.479 | D112: ='US Raw Data'!D115 -> 7583.663 | E112: ='US Raw Data'!E115 -> 1227.495 | F112: =D112-E112 -> 6356.168 | G112: ='US Raw Data'!F115*(B112*4/100) -> 154056.04 | H112: =F112-C112+E112+G111 -> 152235.4 | I112: =G112-H112 -> 1820.6378 | J112: =F112-C112+E112+J111 -> 120026.83 | K112: =F112-C112+E112+I112+K111 -> 154056.04 | M112: =400*F112/(4*B111) -> 20.439136 | N112: =400*C112/(4*B111) -> 18.967374 | O112: =100*G112/(4*B112) -> 122.56815 | P112: =100*G112/(4*B111) -> 123.84711 | Q112: =400*E112/(4*B111)*(1/(O111/100)) -> 3.2613571 | R112: =400*I112/(4*B111) -> 5.8545122 | S112: =((1/4)*(M112-N112+R112)+(1+(Q112/400))*O111) -> 123.84711 | T112: =((1/4)*(M112-N112+R112)+(1+(Q112/400))*O111)*(B111/B112) -> 122.56815 | U112: =(1/4)*(M112-N112+R112)+(1+(Q112/400))*V111 -> 123.84711 | V112: =U112*(B111/B112) -> 122.56815

Sheet US Construction
A1: US CONSTRUCTION - BVAR fiscal inputs from raw cells (LIVE FORMULAS)
A2: Every value is a LIVE formula referencing 'US Raw Data'. US flows are SAAR (already annual): ratios are flow_t/GDP_t with NO *4. Lags reference the row ABOVE on Raw Data; the first row here is 1998Q3 (1998Q2 sits on Raw Data only to supply that lag). Column C is the RAW (no-COVID) FPEXP; column D is the FPEXP that ACTUALLY entered the BVAR (= raw, except interpolated across 2020Q2-2021Q4). FREV (B) and DSVC (G) are untreated.
A4: Date | B4: FREV_GDP (% GDP) | C4: FPEXP_GDP RAW (% GDP) | D4: FPEXP_GDP into BVAR (% GDP) | E4: net interest ($bn) | F4: EFFI (% p.a.) | G4: d_{t-1} (% GDP) | H4: DSVC (% GDP)
B5: FREV = FGRECPT / GDP * 100 | C5: raw primary exp = (FGEXPND - A091) / GDP * 100 [no COVID treatment] | D5: = raw, EXCEPT linearly interpolated across 2020Q2-2021Q4 (COVID outlier) | E5: = A091 (SAAR) - the debt-service $ cost | F5: EFFI = A091 / [ (debt/GDP_{t-1}/100) * GDP_{t-1} ] * 100 | G5: = GFDEGDQ188S of the previous quarter (lagged debt ratio) | H5: DSVC = A091 / GDP_{t-1} * 100 = EFFI * d_{t-1}/100 (DEBT SERVICE)
A6: ='US Raw Data'!A6 -> 1998-Q3 | B6: ='US Raw Data'!C6/'US Raw Data'!B6*100 -> 19.827078 | C6: =('US Raw Data'!D6-'US Raw Data'!E6)/'US Raw Data'!B6*100 -> 15.593892 | D6: =C6 -> 15.593892 | E6: ='US Raw Data'!E6 -> 366.204 | F6: ='US Raw Data'!E6/(('US Raw Data'!F5/100)*'US Raw Data'!B5)*100 -> 6.6007266 | G6: ='US Raw Data'!F5 -> 61.85196 | H6: ='US Raw Data'!E6/'US Raw Data'!B5*100 -> 4.0826788
A7: ='US Raw Data'!A7 -> 1998-Q4 | B7: ='US Raw Data'!C7/'US Raw Data'!B7*100 -> 19.744854 | C7: =('US Raw Data'!D7-'US Raw Data'!E7)/'US Raw Data'!B7*100 -> 15.649144 | D7: =C7 -> 15.649144 | E7: ='US Raw Data'!E7 -> 360.088 | F7: ='US Raw Data'!E7/(('US Raw Data'!F6/100)*'US Raw Data'!B6)*100 -> 6.5160233 | G7: ='US Raw Data'!F6 -> 60.58693 | H7: ='US Raw Data'!E7/'US Raw Data'!B6*100 -> 3.9478585
A8: ='US Raw Data'!A8 -> 1999-Q1 | B8: ='US Raw Data'!C8/'US Raw Data'!B8*100 -> 19.762695 | C8: =('US Raw Data'!D8-'US Raw Data'!E8)/'US Raw Data'!B8*100 -> 15.506176 | D8: =C8 -> 15.506176 | E8: ='US Raw Data'!E8 -> 352.596 | F8: ='US Raw Data'!E8/(('US Raw Data'!F7/100)*'US Raw Data'!B7)*100 -> 6.2804123 | G8: ='US Raw Data'!F7 -> 60.40696 | H8: ='US Raw Data'!E8/'US Raw Data'!B7*100 -> 3.7938061
A9: ='US Raw Data'!A9 -> 1999-Q2 | B9: ='US Raw Data'!C9/'US Raw Data'!B9*100 -> 19.789444 | C9: =('US Raw Data'!D9-'US Raw Data'!E9)/'US Raw Data'!B9*100 -> 15.376734 | D9: =C9 -> 15.376734 | E9: ='US Raw Data'!E9 -> 352.141 | F9: ='US Raw Data'!E9/(('US Raw Data'!F8/100)*'US Raw Data'!B8)*100 -> 6.2308027 | G9: ='US Raw Data'!F8 -> 60.04894 | H9: ='US Raw Data'!E9/'US Raw Data'!B8*100 -> 3.741531
A10: ='US Raw Data'!A10 -> 1999-Q3 | B10: ='US Raw Data'!C10/'US Raw Data'!B10*100 -> 19.768101 | C10: =('US Raw Data'!D10-'US Raw Data'!E10)/'US Raw Data'!B10*100 -> 15.404043 | D10: =C10 -> 15.404043 | E10: ='US Raw Data'!E10 -> 351.073 | F10: ='US Raw Data'!E10/(('US Raw Data'!F9/100)*'US Raw Data'!B9)*100 -> 6.2260454 | G10: ='US Raw Data'!F9 -> 59.19227 | H10: ='US Raw Data'!E10/'US Raw Data'!B9*100 -> 3.6853376
A11: ='US Raw Data'!A11 -> 1999-Q4 | B11: ='US Raw Data'!C11/'US Raw Data'!B11*100 -> 19.835581 | C11: =('US Raw Data'!D11-'US Raw Data'!E11)/'US Raw Data'!B11*100 -> 15.375788 | D11: =C11 -> 15.375788 | E11: ='US Raw Data'!E11 -> 352.925 | F11: ='US Raw Data'!E11/(('US Raw Data'!F10/100)*'US Raw Data'!B10)*100 -> 6.239535 | G11: ='US Raw Data'!F10 -> 58.39258 | H11: ='US Raw Data'!E11/'US Raw Data'!B10*100 -> 3.6434255
A12: ='US Raw Data'!A12 -> 2000-Q1 | B12: ='US Raw Data'!C12/'US Raw Data'!B12*100 -> 20.413192 | C12: =('US Raw Data'!D12-'US Raw Data'!E12)/'US Raw Data'!B12*100 -> 15.111567 | D12: =C12 -> 15.111567 | E12: ='US Raw Data'!E12 -> 354.822 | F12: ='US Raw Data'!E12/(('US Raw Data'!F11/100)*'US Raw Data'!B11)*100 -> 6.1429431 | G12: ='US Raw Data'!F11 -> 58.34336 | H12: ='US Raw Data'!E12/'US Raw Data'!B11*100 -> 3.5839994
A13: ='US Raw Data'!A13 -> 2000-Q2 | B13: ='US Raw Data'!C13/'US Raw Data'!B13*100 -> 20.065722 | C13: =('US Raw Data'!D13-'US Raw Data'!E13)/'US Raw Data'!B13*100 -> 15.169579 | D13: =C13 -> 15.169579 | E13: ='US Raw Data'!E13 -> 354.109 | F13: ='US Raw Data'!E13/(('US Raw Data'!F12/100)*'US Raw Data'!B12)*100 -> 6.1334657 | G13: ='US Raw Data'!F12 -> 57.72134 | H13: ='US Raw Data'!E13/'US Raw Data'!B12*100 -> 3.5403186
A14: ='US Raw Data'!A14 -> 2000-Q3 | B14: ='US Raw Data'!C14/'US Raw Data'!B14*100 -> 20.122454 | C14: =('US Raw Data'!D14-'US Raw Data'!E14)/'US Raw Data'!B14*100 -> 15.174597 | D14: =C14 -> 15.174597 | E14: ='US Raw Data'!E14 -> 352.877 | F14: ='US Raw Data'!E14/(('US Raw Data'!F13/100)*'US Raw Data'!B13)*100 -> 6.206135 | G14: ='US Raw Data'!F13 -> 55.48491 | H14: ='US Raw Data'!E14/'US Raw Data'!B13*100 -> 3.4434684
A15: ='US Raw Data'!A15 -> 2000-Q4 | B15: ='US Raw Data'!C15/'US Raw Data'!B15*100 -> 20.092444 | C15: =('US Raw Data'!D15-'US Raw Data'!E15)/'US Raw Data'!B15*100 -> 15.194805 | D15: =C15 -> 15.194805 | E15: ='US Raw Data'!E15 -> 353.105 | F15: ='US Raw Data'!E15/(('US Raw Data'!F14/100)*'US Raw Data'!B14)*100 -> 6.2230151 | G15: ='US Raw Data'!F14 -> 54.99213 | H15: ='US Raw Data'!E15/'US Raw Data'!B14*100 -> 3.4221686
A16: ='US Raw Data'!A16 -> 2001-Q1 | B16: ='US Raw Data'!C16/'US Raw Data'!B16*100 -> 20.162478 | C16: =('US Raw Data'!D16-'US Raw Data'!E16)/'US Raw Data'!B16*100 -> 15.636207 | D16: =C16 -> 15.636207 | E16: ='US Raw Data'!E16 -> 345.479 | F16: ='US Raw Data'!E16/(('US Raw Data'!F15/100)*'US Raw Data'!B15)*100 -> 6.1014809 | G16: ='US Raw Data'!F15 -> 54.2579 | H16: ='US Raw Data'!E16/'US Raw Data'!B15*100 -> 3.3105354
A17: ='US Raw Data'!A17 -> 2001-Q2 | B17: ='US Raw Data'!C17/'US Raw Data'!B17*100 -> 19.797707 | C17: =('US Raw Data'!D17-'US Raw Data'!E17)/'US Raw Data'!B17*100 -> 15.744929 | D17: =C17 -> 15.744929 | E17: ='US Raw Data'!E17 -> 334.776 | F17: ='US Raw Data'!E17/(('US Raw Data'!F16/100)*'US Raw Data'!B16)*100 -> 5.7982523 | G17: ='US Raw Data'!F16 -> 55.14434 | H17: ='US Raw Data'!E17/'US Raw Data'!B16*100 -> 3.197408
... A92: ='US Raw Data'!A92 -> 2020-Q1 | B92: ='US Raw Data'!C92/'US Raw Data'!B92*100 -> 17.429895 | C92: =('US Raw Data'!D92-'US Raw Data'!E92)/'US Raw Data'!B92*100 -> 19.872437 | D92: =C92 -> 19.872437 | E92: ='US Raw Data'!E92 -> 544.122 | F92: ='US Raw Data'!E92/(('US Raw Data'!F91/100)*'US Raw Data'!B91)*100 -> 2.3452139 | G92: ='US Raw Data'!F91 -> 105.78193 | H92: ='US Raw Data'!E92/'US Raw Data'!B91*100 -> 2.4808126
A93: ='US Raw Data'!A93 -> 2020-Q2 | B93: ='US Raw Data'!C93/'US Raw Data'!B93*100 -> 17.709487 | C93: =('US Raw Data'!D93-'US Raw Data'!E93)/'US Raw Data'!B93*100 -> 41.970708 | D93: =C92+(C100-C92)*0.125 -> 20.044705 | E93: ='US Raw Data'!E93 -> 514.737 | F93: ='US Raw Data'!E93/(('US Raw Data'!F92/100)*'US Raw Data'!B92)*100 -> 2.2164191 | G93: ='US Raw Data'!F92 -> 106.77007 | H93: ='US Raw Data'!E93/'US Raw Data'!B92*100 -> 2.3664722
A94: ='US Raw Data'!A94 -> 2020-Q3 | B94: ='US Raw Data'!C94/'US Raw Data'!B94*100 -> 17.496768 | C94: =('US Raw Data'!D94-'US Raw Data'!E94)/'US Raw Data'!B94*100 -> 30.713075 | D94: =C92+(C100-C92)*0.25 -> 20.216974 | E94: ='US Raw Data'!E94 -> 508.011 | F94: ='US Raw Data'!E94/(('US Raw Data'!F93/100)*'US Raw Data'!B93)*100 -> 1.9186704 | G94: ='US Raw Data'!F93 -> 132.66287 | H94: ='US Raw Data'!E94/'US Raw Data'!B93*100 -> 2.5453632
A95: ='US Raw Data'!A95 -> 2020-Q4 | B95: ='US Raw Data'!C95/'US Raw Data'!B95*100 -> 17.853617 | C95: =('US Raw Data'!D95-'US Raw Data'!E95)/'US Raw Data'!B95*100 -> 24.501258 | D95: =C92+(C100-C92)*0.375 -> 20.389243 | E95: ='US Raw Data'!E95 -> 516.711 | F95: ='US Raw Data'!E95/(('US Raw Data'!F94/100)*'US Raw Data'!B94)*100 -> 1.917623 | G95: ='US Raw Data'!F94 -> 124.14692 | H95: ='US Raw Data'!E95/'US Raw Data'!B94*100 -> 2.3806699
A96: ='US Raw Data'!A96 -> 2021-Q1 | B96: ='US Raw Data'!C96/'US Raw Data'!B96*100 -> 18.232873 | C96: =('US Raw Data'!D96-'US Raw Data'!E96)/'US Raw Data'!B96*100 -> 34.4468 | D96: =C92+(C100-C92)*0.5 -> 20.561512 | E96: ='US Raw Data'!E96 -> 533.518 | F96: ='US Raw Data'!E96/(('US Raw Data'!F95/100)*'US Raw Data'!B95)*100 -> 1.9227399 | G96: ='US Raw Data'!F95 -> 125.62864 | H96: ='US Raw Data'!E96/'US Raw Data'!B95*100 -> 2.415512
A97: ='US Raw Data'!A97 -> 2021-Q2 | B97: ='US Raw Data'!C97/'US Raw Data'!B97*100 -> 18.649581 | C97: =('US Raw Data'!D97-'US Raw Data'!E97)/'US Raw Data'!B97*100 -> 30.708267 | D97: =C92+(C100-C92)*0.625 -> 20.733781 | E97: ='US Raw Data'!E97 -> 560.634 | F97: ='US Raw Data'!E97/(('US Raw Data'!F96/100)*'US Raw Data'!B96)*100 -> 1.992829 | G97: ='US Raw Data'!F96 -> 124.03752 | H97: ='US Raw Data'!E97/'US Raw Data'!B96*100 -> 2.4718557
A98: ='US Raw Data'!A98 -> 2021-Q3 | B98: ='US Raw Data'!C98/'US Raw Data'!B98*100 -> 18.860264 | C98: =('US Raw Data'!D98-'US Raw Data'!E98)/'US Raw Data'!B98*100 -> 25.88438 | D98: =C92+(C100-C92)*0.75 -> 20.90605 | E98: ='US Raw Data'!E98 -> 587.92 | F98: ='US Raw Data'!E98/(('US Raw Data'!F97/100)*'US Raw Data'!B97)*100 -> 2.0607487 | G98: ='US Raw Data'!F97 -> 121.78582 | H98: ='US Raw Data'!E98/'US Raw Data'!B97*100 -> 2.5096997
A99: ='US Raw Data'!A99 -> 2021-Q4 | B99: ='US Raw Data'!C99/'US Raw Data'!B99*100 -> 18.89706 | C99: =('US Raw Data'!D99-'US Raw Data'!E99)/'US Raw Data'!B99*100 -> 22.679998 | D99: =C92+(C100-C92)*0.875 -> 21.078318 | E99: ='US Raw Data'!E99 -> 612.282 | F99: ='US Raw Data'!E99/(('US Raw Data'!F98/100)*'US Raw Data'!B98)*100 -> 2.1537295 | G99: ='US Raw Data'!F98 -> 118.54086 | H99: ='US Raw Data'!E99/'US Raw Data'!B98*100 -> 2.5530495
A100: ='US Raw Data'!A100 -> 2022-Q1 | B100: ='US Raw Data'!C100/'US Raw Data'!B100*100 -> 20.099177 | C100: =('US Raw Data'!D100-'US Raw Data'!E100)/'US Raw Data'!B100*100 -> 21.250587 | D100: =C100 -> 21.250587 | E100: ='US Raw Data'!E100 -> 636.968 | F100: ='US Raw Data'!E100/(('US Raw Data'!F99/100)*'US Raw Data'!B99)*100 -> 2.1506681 | G100: ='US Raw Data'!F99 -> 119.3588 | H100: ='US Raw Data'!E100/'US Raw Data'!B99*100 -> 2.5670116
A101: ='US Raw Data'!A101 -> 2022-Q2 | B101: ='US Raw Data'!C101/'US Raw Data'!B101*100 -> 19.85511 | C101: =('US Raw Data'!D101-'US Raw Data'!E101)/'US Raw Data'!B101*100 -> 20.860972 | D101: =C101 -> 20.860972 | E101: ='US Raw Data'!E101 -> 684.758 | F101: ='US Raw Data'!E101/(('US Raw Data'!F100/100)*'US Raw Data'!B100)*100 -> 2.2524222 | G101: ='US Raw Data'!F100 -> 120.39819 | H101: ='US Raw Data'!E101/'US Raw Data'!B100*100 -> 2.7118756
A102: ='US Raw Data'!A102 -> 2022-Q3 | B102: ='US Raw Data'!C102/'US Raw Data'!B102*100 -> 19.552546 | C102: =('US Raw Data'!D102-'US Raw Data'!E102)/'US Raw Data'!B102*100 -> 20.60523 | D102: =C102 -> 20.60523 | E102: ='US Raw Data'!E102 -> 752.081 | F102: ='US Raw Data'!E102/(('US Raw Data'!F101/100)*'US Raw Data'!B101)*100 -> 2.4603071 | G102: ='US Raw Data'!F101 -> 118.20207 | H102: ='US Raw Data'!E102/'US Raw Data'!B101*100 -> 2.9081339
A103: ='US Raw Data'!A103 -> 2022-Q4 | B103: ='US Raw Data'!C103/'US Raw Data'!B103*100 -> 19.061136 | C103: =('US Raw Data'!D103-'US Raw Data'!E103)/'US Raw Data'!B103*100 -> 20.527189 | D103: =C103 -> 20.527189 | E103: ='US Raw Data'!E103 -> 823.106 | F103: ='US Raw Data'!E103/(('US Raw Data'!F102/100)*'US Raw Data'!B102)*100 -> 2.6612833 | G103: ='US Raw Data'!F102 -> 117.43832 | H103: ='US Raw Data'!E103/'US Raw Data'!B102*100 -> 3.1253664
A104: ='US Raw Data'!A104 -> 2023-Q1 | B104: ='US Raw Data'!C104/'US Raw Data'!B104*100 -> 17.460014 | C104: =('US Raw Data'!D104-'US Raw Data'!E104)/'US Raw Data'!B104*100 -> 20.47414 | D104: =C104 -> 20.47414 | E104: ='US Raw Data'!E104 -> 861.267 | F104: ='US Raw Data'!E104/(('US Raw Data'!F103/100)*'US Raw Data'!B103)*100 -> 2.7411696 | G104: ='US Raw Data'!F103 -> 117.36678 | H104: ='US Raw Data'!E104/'US Raw Data'!B103*100 -> 3.2172225
A105: ='US Raw Data'!A105 -> 2023-Q2 | B105: ='US Raw Data'!C105/'US Raw Data'!B105*100 -> 17.324401 | C105: =('US Raw Data'!D105-'US Raw Data'!E105)/'US Raw Data'!B105*100 -> 20.332655 | D105: =C105 -> 20.332655 | E105: ='US Raw Data'!E105 -> 894.106 | F105: ='US Raw Data'!E105/(('US Raw Data'!F104/100)*'US Raw Data'!B104)*100 -> 2.8421818 | G105: ='US Raw Data'!F104 -> 115.58614 | H105: ='US Raw Data'!E105/'US Raw Data'!B104*100 -> 3.2851682
A106: ='US Raw Data'!A106 -> 2023-Q3 | B106: ='US Raw Data'!C106/'US Raw Data'!B106*100 -> 17.22377 | C106: =('US Raw Data'!D106-'US Raw Data'!E106)/'US Raw Data'!B106*100 -> 19.917245 | D106: =C106 -> 19.917245 | E106: ='US Raw Data'!E106 -> 966.899 | F106: ='US Raw Data'!E106/(('US Raw Data'!F105/100)*'US Raw Data'!B105)*100 -> 2.9905073 | G106: ='US Raw Data'!F105 -> 117.44355 | H106: ='US Raw Data'!E106/'US Raw Data'!B105*100 -> 3.5121579
A107: ='US Raw Data'!A107 -> 2023-Q4 | B107: ='US Raw Data'!C107/'US Raw Data'!B107*100 -> 17.331906 | C107: =('US Raw Data'!D107-'US Raw Data'!E107)/'US Raw Data'!B107*100 -> 19.830097 | D107: =C107 -> 19.830097 | E107: ='US Raw Data'!E107 -> 1031.478 | F107: ='US Raw Data'!E107/(('US Raw Data'!F106/100)*'US Raw Data'!B106)*100 -> 3.1099214 | G107: ='US Raw Data'!F106 -> 118.13897 | H107: ='US Raw Data'!E107/'US Raw Data'!B106*100 -> 3.6740291
A108: ='US Raw Data'!A108 -> 2024-Q1 | B108: ='US Raw Data'!C108/'US Raw Data'!B108*100 -> 17.576326 | C108: =('US Raw Data'!D108-'US Raw Data'!E108)/'US Raw Data'!B108*100 -> 20.116053 | D108: =C108 -> 20.116053 | E108: ='US Raw Data'!E108 -> 1071.174 | F108: ='US Raw Data'!E108/(('US Raw Data'!F107/100)*'US Raw Data'!B107)*100 -> 3.1503734 | G108: ='US Raw Data'!F107 -> 119.61944 | H108: ='US Raw Data'!E108/'US Raw Data'!B107*100 -> 3.768459
A109: ='US Raw Data'!A109 -> 2024-Q2 | B109: ='US Raw Data'!C109/'US Raw Data'!B109*100 -> 17.657015 | C109: =('US Raw Data'!D109-'US Raw Data'!E109)/'US Raw Data'!B109*100 -> 20.07221 | D109: =C109 -> 20.07221 | E109: ='US Raw Data'!E109 -> 1103.565 | F109: ='US Raw Data'!E109/(('US Raw Data'!F108/100)*'US Raw Data'!B108)*100 -> 3.1907361 | G109: ='US Raw Data'!F108 -> 120.47631 | H109: ='US Raw Data'!E109/'US Raw Data'!B108*100 -> 3.8440811
A110: ='US Raw Data'!A110 -> 2024-Q3 | B110: ='US Raw Data'!C110/'US Raw Data'!B110*100 -> 17.654426 | C110: =('US Raw Data'!D110-'US Raw Data'!E110)/'US Raw Data'!B110*100 -> 20.396956 | D110: =C110 -> 20.396956 | E110: ='US Raw Data'!E110 -> 1146.182 | F110: ='US Raw Data'!E110/(('US Raw Data'!F109/100)*'US Raw Data'!B109)*100 -> 3.2906353 | G110: ='US Raw Data'!F109 -> 119.50314 | H110: ='US Raw Data'!E110/'US Raw Data'!B109*100 -> 3.9324125
A111: ='US Raw Data'!A111 -> 2024-Q4 | B111: ='US Raw Data'!C111/'US Raw Data'!B111*100 -> 17.814453 | C111: =('US Raw Data'!D111-'US Raw Data'!E111)/'US Raw Data'!B111*100 -> 20.425847 | D111: =C111 -> 20.425847 | E111: ='US Raw Data'!E111 -> 1155.616 | F111: ='US Raw Data'!E111/(('US Raw Data'!F110/100)*'US Raw Data'!B110)*100 -> 3.2584988 | G111: ='US Raw Data'!F110 -> 120.17172 | H111: ='US Raw Data'!E111/'US Raw Data'!B110*100 -> 3.9157941
... A115: ='US Raw Data'!A115 -> 2025-Q4 | B115: ='US Raw Data'!C115/'US Raw Data'!B115*100 -> 18.771499 | C115: =('US Raw Data'!D115-'US Raw Data'!E115)/'US Raw Data'!B115*100 -> 20.228062 | D115: =C115 -> 20.228062 | E115: ='US Raw Data'!E115 -> 1227.495 | F115: ='US Raw Data'!E115/(('US Raw Data'!F114/100)*'US Raw Data'!B114)*100 -> 3.2613571 | G115: ='US Raw Data'!F114 -> 121.02875 | H115: ='US Raw Data'!E115/'US Raw Data'!B114*100 -> 3.9471797

Sheet US Fiscal Arithmetic
A1: US FISCAL ARITHMETIC - decompose the OBSERVED debt/GDP change (LIVE)
A2: A one-step decomposition of the OBSERVED debt change: each row rolls forward from the OBSERVED d_{t-1}, so it is an exact quarter-by-quarter accounting. Same budget identity in two forms: RATIO form (the app): d_t = d_{t-1}*(1+i_eff/400)/(1+gNomQ/100) - pb/4 + sfa/4 LEVEL form (your concept): B_t = (1+i_eff/400)*B_{t-1} - PB$_t + SFA$_t , then d_t = B_t/GDPann_t*100. pb = FREV - FPEXP. SFA (col H) is a COMPUTED residual = the part of the observed debt change NOT explained by interest+growth+primary balance (the deficit-debt discrepancy: valuation, below-the-line financing). It is NOT a zero input - it is informative. With it, BOTH forms reproduce OBSERVED debt/GDP to the last digit (col L = 0).
A4: Date | B4: pb (% GDP) | C4: DSVC = interest (% GDP) | D4: i_eff (% p.a.) | E4: gNomQ (% / quarter) | F4: d_{t-1} OBSERVED (% GDP) | G4: snowball (pp) | H4: SFA (% GDP, residual) | I4: d_t RATIO form (% GDP) | J4: B_t LEVEL ($/GBP) | K4: d_t from LEVEL (% GDP) | L4: OBSERVED d_t (% GDP) | M4: recon - observed (pp)
B5: primary balance = FREV - FPEXP (FPEXP as it ENTERED the BVAR) | C5: debt service from Construction (the estimated driver) | D5: effective rate, BACKED OUT: i_eff = DSVC*100 / d_{t-1} | E5: US: 100*(GDP_t/GDP_{t-1}-1), SAAR. UK: 100*(4qGDP_t/4qGDP_{t-1}-1) | F5: lagged OBSERVED debt ratio (the decomposition starts from data each step) | G5: = [(1+i_eff/400)/(1+gNomQ/100) - 1] * d_{t-1} (automatic debt dynamics) | H5: = 4*(d_obs_t - d_{t-1} - snowball + pb/4) (deficit-debt discrepancy, COMPUTED) | I5: = d_{t-1}(1+i_eff/400)/(1+gNomQ/100) - pb/4 + sfa/4 | J5: = (1+i_eff/400)*B_{t-1} - PB$_t + SFA$_t ; B_{t-1}=d_{t-1}/100*GDPann_{t-1} | K5: = B_t / GDPann_t * 100 (must equal the RATIO-form d_t) | L5: US: GFDEGDQ188S; UK: 100*gross_debt_t/4qGDP_t (back-cast TARGET) | M5: = d_t(ratio) - observed (the CHECK, ~0 with the SFA residual)
A6: ='US Construction'!A6 -> 1998-Q3 | B6: ='US Construction'!B6-'US Construction'!D6 -> 4.233186 | C6: ='US Construction'!H6 -> 4.0826788 | D6: =C6*100/F6 -> 6.7385471 | E6: =100*('US Raw Data'!B6/'US Raw Data'!B5-1) -> 1.6878827 | F6: ='US Raw Data'!F6 -> 60.58693 | G6: =((1+D6/400)/(1+E6/100)-1)*F6 -> -0.001933981 | H6: =4*(L6-F6-G6+B6/4) -> 4.2409219 | I6: =F6*(1+D6/400)/(1+E6/100)-B6/4+H6/4 -> 60.58693 | J6: =(1+D6/400)*(F6/100*'US Raw Data'!B5)-B6/100*'US Raw Data'!B6/4+H6/100*'US Raw Data'!B6/4 -> 5526.1927 | K6: =J6/'US Raw Data'!B6*100 -> 60.58693 | L6: ='US Raw Data'!F6 -> 60.58693 | M6: =I6-L6 -> 0
A7: ='US Construction'!A7 -> 1998-Q4 | B7: ='US Construction'!B7-'US Construction'!D7 -> 4.0957109 | C7: ='US Construction'!H7 -> 3.9478585 | D7: =C7*100/F7 -> 6.5160233 | E7: =100*('US Raw Data'!B7/'US Raw Data'!B6-1) -> 1.8955395 | F7: ='US Raw Data'!F6 -> 60.58693 | G7: =((1+D7/400)/(1+E7/100)-1)*F7 -> -0.15848054 | H7: =4*(L7-F7-G7+B7/4) -> 4.009753 | I7: =F7*(1+D7/400)/(1+E7/100)-B7/4+H7/4 -> 60.40696 | J7: =(1+D7/400)*(F7/100*'US Raw Data'!B6)-B7/100*'US Raw Data'!B7/4+H7/100*'US Raw Data'!B7/4 -> 5614.2174 | K7: =J7/'US Raw Data'!B7*100 -> 60.40696 | L7: ='US Raw Data'!F7 -> 60.40696 | M7: =I7-L7 -> 0
A8: ='US Construction'!A8 -> 1999-Q1 | B8: ='US Construction'!B8-'US Construction'!D8 -> 4.2565187 | C8: ='US Construction'!H8 -> 3.7938061 | D8: =C8*100/F8 -> 6.2804123 | E8: =100*('US Raw Data'!B8/'US Raw Data'!B7-1) -> 1.2663128 | F8: ='US Raw Data'!F7 -> 60.40696 | G8: =((1+D8/400)/(1+E8/100)-1)*F8 -> 0.18121569 | H8: =4*(L8-F8-G8+B8/4) -> 2.0995759 | I8: =F8*(1+D8/400)/(1+E8/100)-B8/4+H8/4 -> 60.04894 | J8: =(1+D8/400)*(F8/100*'US Raw Data'!B7)-B8/100*'US Raw Data'!B8/4+H8/100*'US Raw Data'!B8/4 -> 5651.6153 | K8: =J8/'US Raw Data'!B8*100 -> 60.04894 | L8: ='US Raw Data'!F8 -> 60.04894 | M8: =I8-L8 -> 0
A9: ='US Construction'!A9 -> 1999-Q2 | B9: ='US Construction'!B9-'US Construction'!D9 -> 4.4127098 | C9: ='US Construction'!H9 -> 3.741531 | D9: =C9*100/F9 -> 6.2308027 | E9: =100*('US Raw Data'!B9/'US Raw Data'!B8-1) -> 1.2168707 | F9: ='US Raw Data'!F8 -> 60.04894 | G9: =((1+D9/400)/(1+E9/100)-1)*F9 -> 0.20220423 | H9: =4*(L9-F9-G9+B9/4) -> 0.17721284 | I9: =F9*(1+D9/400)/(1+E9/100)-B9/4+H9/4 -> 59.19227 | J9: =(1+D9/400)*(F9/100*'US Raw Data'!B8)-B9/100*'US Raw Data'!B9/4+H9/100*'US Raw Data'!B9/4 -> 5638.7799 | K9: =J9/'US Raw Data'!B9*100 -> 59.19227 | L9: ='US Raw Data'!F9 -> 59.19227 | M9: =I9-L9 -> 0
A10: ='US Construction'!A10 -> 1999-Q3 | B10: ='US Construction'!B10-'US Construction'!D10 -> 4.3640582 | C10: ='US Construction'!H10 -> 3.6853376 | D10: =C10*100/F10 -> 6.2260454 | E10: =100*('US Raw Data'!B10/'US Raw Data'!B9-1) -> 1.6839436 | F10: ='US Raw Data'!F9 -> 59.19227 | G10: =((1+D10/400)/(1+E10/100)-1)*F10 -> -0.074180854 | H10: =4*(L10-F10-G10+B10/4) -> 1.4620217 | I10: =F10*(1+D10/400)/(1+E10/100)-B10/4+H10/4 -> 58.39258 | J10: =(1+D10/400)*(F10/100*'US Raw Data'!B9)-B10/100*'US Raw Data'!B10/4+H10/100*'US Raw Data'!B10/4 -> 5656.2708 | K10: =J10/'US Raw Data'!B10*100 -> 58.39258 | L10: ='US Raw Data'!F10 -> 58.39258 | M10: =I10-L10 -> 0
A11: ='US Construction'!A11 -> 1999-Q4 | B11: ='US Construction'!B11-'US Construction'!D11 -> 4.4597926 | C11: ='US Construction'!H11 -> 3.6434255 | D11: =C11*100/F11 -> 6.239535 | E11: =100*('US Raw Data'!B11/'US Raw Data'!B10-1) -> 2.2045137 | F11: ='US Raw Data'!F10 -> 58.39258 | G11: =((1+D11/400)/(1+E11/100)-1)*F11 -> -0.36829692 | H11: =4*(L11-F11-G11+B11/4) -> 5.7361002 | I11: =F11*(1+D11/400)/(1+E11/100)-B11/4+H11/4 -> 58.34336 | J11: =(1+D11/400)*(F11/100*'US Raw Data'!B10)-B11/100*'US Raw Data'!B11/4+H11/100*'US Raw Data'!B11/4 -> 5776.0912 | K11: =J11/'US Raw Data'!B11*100 -> 58.34336 | L11: ='US Raw Data'!F11 -> 58.34336 | M11: =I11-L11 -> 0
A12: ='US Construction'!A12 -> 2000-Q1 | B12: ='US Construction'!B12-'US Construction'!D12 -> 5.3016248 | C12: ='US Construction'!H12 -> 3.5839994 | D12: =C12*100/F12 -> 6.1429431 | E12: =100*('US Raw Data'!B12/'US Raw Data'!B11-1) -> 1.0303865 | F12: ='US Raw Data'!F11 -> 58.34336 | G12: =((1+D12/400)/(1+E12/100)-1)*F12 -> 0.29183079 | H12: =4*(L12-F12-G12+B12/4) -> 1.6462216 | I12: =F12*(1+D12/400)/(1+E12/100)-B12/4+H12/4 -> 57.72134 | J12: =(1+D12/400)*(F12/100*'US Raw Data'!B11)-B12/100*'US Raw Data'!B12/4+H12/100*'US Raw Data'!B12/4 -> 5773.3917 | K12: =J12/'US Raw Data'!B12*100 -> 57.72134 | L12: ='US Raw Data'!F12 -> 57.72134 | M12: =I12-L12 -> 0
A13: ='US Construction'!A13 -> 2000-Q2 | B13: ='US Construction'!B13-'US Construction'!D13 -> 4.8961428 | C13: ='US Construction'!H13 -> 3.5403186 | D13: =C13*100/F13 -> 6.1334657 | E13: =100*('US Raw Data'!B13/'US Raw Data'!B12-1) -> 2.4548751 | F13: ='US Raw Data'!F12 -> 57.72134 | G13: =((1+D13/400)/(1+E13/100)-1)*F13 -> -0.51916236 | H13: =4*(L13-F13-G13+B13/4) -> -1.9729278 | I13: =F13*(1+D13/400)/(1+E13/100)-B13/4+H13/4 -> 55.48491 | J13: =(1+D13/400)*(F13/100*'US Raw Data'!B12)-B13/100*'US Raw Data'!B13/4+H13/100*'US Raw Data'!B13/4 -> 5685.9382 | K13: =J13/'US Raw Data'!B13*100 -> 55.48491 | L13: ='US Raw Data'!F13 -> 55.48491 | M13: =I13-L13 -> 0
A14: ='US Construction'!A14 -> 2000-Q3 | B14: ='US Construction'!B14-'US Construction'!D14 -> 4.9478565 | C14: ='US Construction'!H14 -> 3.4434684 | D14: =C14*100/F14 -> 6.206135 | E14: =100*('US Raw Data'!B14/'US Raw Data'!B13-1) -> 0.6874212 | F14: ='US Raw Data'!F13 -> 55.48491 | G14: =((1+D14/400)/(1+E14/100)-1)*F14 -> 0.47617871 | H14: =4*(L14-F14-G14+B14/4) -> 1.0720217 | I14: =F14*(1+D14/400)/(1+E14/100)-B14/4+H14/4 -> 54.99213 | J14: =(1+D14/400)*(F14/100*'US Raw Data'!B13)-B14/100*'US Raw Data'!B14/4+H14/100*'US Raw Data'!B14/4 -> 5674.1787 | K14: =J14/'US Raw Data'!B14*100 -> 54.99213 | L14: ='US Raw Data'!F14 -> 54.99213 | M14: =I14-L14 -> 0
A15: ='US Construction'!A15 -> 2000-Q4 | B15: ='US Construction'!B15-'US Construction'!D15 -> 4.8976383 | C15: ='US Construction'!H15 -> 3.4221686 | D15: =C15*100/F15 -> 6.2230151 | E15: =100*('US Raw Data'!B15/'US Raw Data'!B14-1) -> 1.139534 | F15: ='US Raw Data'!F14 -> 54.99213 | G15: =((1+D15/400)/(1+E15/100)-1)*F15 -> 0.22630925 | H15: =4*(L15-F15-G15+B15/4) -> 1.0554814 | I15: =F15*(1+D15/400)/(1+E15/100)-B15/4+H15/4 -> 54.2579 | J15: =(1+D15/400)*(F15/100*'US Raw Data'!B14)-B15/100*'US Raw Data'!B15/4+H15/100*'US Raw Data'!B15/4 -> 5662.2155 | K15: =J15/'US Raw Data'!B15*100 -> 54.2579 | L15: ='US Raw Data'!F15 -> 54.2579 | M15: =I15-L15 -> 0
A16: ='US Construction'!A16 -> 2001-Q1 | B16: ='US Construction'!B16-'US Construction'!D16 -> 4.5262707 | C16: ='US Construction'!H16 -> 3.3105354 | D16: =C16*100/F16 -> 6.1014809 | E16: =100*('US Raw Data'!B16/'US Raw Data'!B15-1) -> 0.33046997 | F16: ='US Raw Data'!F15 -> 54.2579 | G16: =((1+D16/400)/(1+E16/100)-1)*F16 -> 0.64619231 | H16: =4*(L16-F16-G16+B16/4) -> 5.4872615 | I16: =F16*(1+D16/400)/(1+E16/100)-B16/4+H16/4 -> 55.14434 | J16: =(1+D16/400)*(F16/100*'US Raw Data'!B15)-B16/100*'US Raw Data'!B16/4+H16/100*'US Raw Data'!B16/4 -> 5773.7398 | K16: =J16/'US Raw Data'!B16*100 -> 55.14434 | L16: ='US Raw Data'!F16 -> 55.14434 | M16: =I16-L16 -> 0
A17: ='US Construction'!A17 -> 2001-Q2 | B17: ='US Construction'!B17-'US Construction'!D17 -> 4.0527786 | C17: ='US Construction'!H17 -> 3.197408 | D17: =C17*100/F17 -> 5.7982523 | E17: =100*('US Raw Data'!B17/'US Raw Data'!B16-1) -> 1.2298583 | F17: ='US Raw Data'!F16 -> 55.14434 | G17: =((1+D17/400)/(1+E17/100)-1)*F17 -> 0.11968285 | H17: =4*(L17-F17-G17+B17/4) -> -0.87671282 | I17: =F17*(1+D17/400)/(1+E17/100)-B17/4+H17/4 -> 54.03165 | J17: =(1+D17/400)*(F17/100*'US Raw Data'!B16)-B17/100*'US Raw Data'!B17/4+H17/100*'US Raw Data'!B17/4 -> 5726.8146 | K17: =J17/'US Raw Data'!B17*100 -> 54.03165 | L17: ='US Raw Data'!F17 -> 54.03165 | M17: =I17-L17 -> 0
A18: ='US Construction'!A18 -> 2001-Q3 | B18: ='US Construction'!B18-'US Construction'!D18 -> 1.8569695 | C18: ='US Construction'!H18 -> 3.0835551 | D18: =C18*100/F18 -> 5.7069422 | E18: =100*('US Raw Data'!B18/'US Raw Data'!B17-1) -> -0.0092461553 | F18: ='US Raw Data'!F17 -> 54.03165 | G18: =((1+D18/400)/(1+E18/100)-1)*F18 -> 0.77595636 | H18: =4*(L18-F18-G18+B18/4) -> 1.8170641 | I18: =F18*(1+D18/400)/(1+E18/100)-B18/4+H18/4 -> 54.79763 | J18: =(1+D18/400)*(F18/100*'US Raw Data'!B17)-B18/100*'US Raw Data'!B18/4+H18/100*'US Raw Data'!B18/4 -> 5807.4638 | K18: =J18/'US Raw Data'!B18*100 -> 54.79763 | L18: ='US Raw Data'!F18 -> 54.79763 | M18: =I18-L18 -> 0
... A115: ='US Construction'!A115 -> 2025-Q4 | B115: ='US Construction'!B115-'US Construction'!D115 -> -1.4565634 | C115: ='US Construction'!H115 -> 3.9471797 | D115: =C115*100/F115 -> 3.2613571 | E115: =100*('US Raw Data'!B115/'US Raw Data'!B114-1) -> 1.0434713 | F115: ='US Raw Data'!F114 -> 121.02875 | G115: =((1+D115/400)/(1+E115/100)-1)*F115 -> -0.27325408 | H115: =4*(L115-F115-G115+B115/4) -> 5.794053 | I115: =F115*(1+D115/400)/(1+E115/100)-B115/4+H115/4 -> 122.56815 | J115: =(1+D115/400)*(F115/100*'US Raw Data'!B114)-B115/100*'US Raw Data'!B115/4+H115/100*'US Raw Data'!B115/4 -> 38514.009 | K115: =J115/'US Raw Data'!B115*100 -> 122.56815 | L115: ='US Raw Data'!F115 -> 122.56815 | M115: =I115-L115 -> 0
A117: EQUIVALENCE: the RATIO-form d_t (col I) and the LEVEL-form d_t (col K) are identical to display precision - your level recursion B_t=(1+i_eff)B_{t-1}-(Exp-Rev)+SFA and the app's ratio recursion are the SAME identity. col M (recon - observed) is ~0 because the SFA residual (col H) closes the identity onto observed. SFA itself is the informative deficit-debt discrepancy (financial transactions / valuation / below-the-line) - read it as a column in its own right.

Sheet US Projection
A1: US PROJECTION - how the BVAR forecasts debt service & debt/GDP AHEAD
A2: The orange columns (FREV, FPEXP, DSVC and its 16/84 bands, plus the forecast 100*log GDP and deflator) ARE the deployed BVAR output, app/public/data/bvar/US/baseline_levels.json, over the 20-quarter forecast starting the quarter after the last history. The BVAR forecasts DSVC (debt service) DIRECTLY as a 'lin' variable. From it the white columns back out the effective rate and roll the debt forward with LIVE formulas, exactly as fiscalAccounting.ts does: i_eff = DSVC*100/d_{t-1} ; gNomQ = Delta(100*log GDP) + Delta(100*log deflator) ; pb = FREV - FPEXP ; d_t = d_{t-1}*(1+i_eff/400)/(1+gNomQ/100) - pb/4. The debt-service $ cost = DSVC/100 * GDP grows as both DSVC (the rate*stock effect) and GDP rise. The 16/84 DSVC band shows the BVAR's forecast uncertainty on the debt-service cost.
A4: Fcst q | B4: FREV_GDP (% GDP) | C4: FPEXP_GDP (% GDP) | D4: DSVC (% GDP) | E4: DSVC q16 (% GDP) | F4: DSVC q84 (% GDP) | G4: 100*log GDP | H4: 100*log deflator | I4: gNomQ (% / q) | J4: pb (% GDP) | K4: i_eff (% p.a.) | L4: d_{t-1} (% GDP) | M4: d_t (% GDP)
B5: BVAR forecast, baseline_levels | C5: BVAR forecast, baseline_levels | D5: BVAR forecast debt service (the estimated driver) | E5: BVAR 16th pctile band | F5: BVAR 84th pctile band | G5: BVAR forecast real GDP (level space) | H5: BVAR forecast GDP deflator (level space) | I5: = Delta(100*log GDP) + Delta(100*log deflator) (nominal growth) | J5: = FREV - FPEXP (primary balance) | K5: = DSVC*100 / d_{t-1} (effective rate, backed out) | L5: lagged debt ratio (seed = d0 = last observed debt/GDP) | M5: = d_{t-1}(1+i_eff/400)/(1+gNomQ/100) - pb/4 (PROJECTED debt/GDP)
A6: f+1 | B6: 19.032 | C6: 20.4829 | D6: 3.95743 | E6: 3.91915 | F6: 3.99384 | G6: 1009.17 | H6: 488.191 | I6: =(G6-1008.81)+(H6-487.232) -> 1.319 | J6: =B6-C6 -> -1.4509 | K6: =D6*100/L6 -> 3.2287589 | L6: =122.56815 -> 122.56815 | M6: =L6*(1+K6/400)/(1+I6/100)-J6/4 -> 122.31173
A7: f+2 | B7: 19.1393 | C7: 20.4896 | D7: 3.94955 | E7: 3.88195 | F7: 4.01306 | G7: 1009.66 | H7: 489.238 | I7: =(G7-G6)+(H7-H6) -> 1.537 | J7: =B7-C7 -> -1.3503 | K7: =D7*100/L7 -> 3.2290854 | L7: =M6 -> 122.31173 | M7: =L7*(1+K7/400)/(1+I7/100)-J7/4 -> 121.77027
A8: f+3 | B8: 19.2987 | C8: 20.5015 | D8: 3.95681 | E8: 3.85117 | F8: 4.05111 | G8: 1010.13 | H8: 490.231 | I8: =(G8-G7)+(H8-H7) -> 1.463 | J8: =B8-C8 -> -1.2028 | K8: =D8*100/L8 -> 3.2494057 | L8: =M7 -> 121.77027 | M8: =L8*(1+K8/400)/(1+I8/100)-J8/4 -> 121.29009
A9: f+4 | B9: 19.3462 | C9: 20.5424 | D9: 3.9784 | E9: 3.83564 | F9: 4.10417 | G9: 1010.65 | H9: 491.186 | I9: =(G9-G8)+(H9-H8) -> 1.475 | J9: =B9-C9 -> -1.1962 | K9: =D9*100/L9 -> 3.28007 | L9: =M8 -> 121.29009 | M9: =L9*(1+K9/400)/(1+I9/100)-J9/4 -> 120.80626
A10: f+5 | B10: 19.4201 | C10: 20.5436 | D10: 4.01202 | E10: 3.82215 | F10: 4.18203 | G10: 1011.23 | H10: 492.136 | I10: =(G10-G9)+(H10-H9) -> 1.53 | J10: =B10-C10 -> -1.1235 | K10: =D10*100/L10 -> 3.3210364 | L10: =M9 -> 120.80626 | M10: =L10*(1+K10/400)/(1+I10/100)-J10/4 -> 120.25455
A11: f+6 | B11: 19.4969 | C11: 20.4949 | D11: 4.05644 | E11: 3.81616 | F11: 4.25917 | G11: 1011.87 | H11: 493.102 | I11: =(G11-G10)+(H11-H10) -> 1.606 | J11: =B11-C11 -> -0.998 | K11: =D11*100/L11 -> 3.3732113 | L11: =M10 -> 120.25455 | M11: =L11*(1+K11/400)/(1+I11/100)-J11/4 -> 119.60137
A12: f+7 | B12: 19.5799 | C12: 20.3888 | D12: 4.1093 | E12: 3.84083 | F12: 4.34629 | G12: 1012.59 | H12: 494.082 | I12: =(G12-G11)+(H12-H11) -> 1.7 | J12: =B12-C12 -> -0.8089 | K12: =D12*100/L12 -> 3.4358303 | L12: =M11 -> 119.60137 | M12: =L12*(1+K12/400)/(1+I12/100)-J12/4 -> 118.81451
A13: f+8 | B13: 19.675 | C13: 20.2493 | D13: 4.16857 | E13: 3.86257 | F13: 4.43066 | G13: 1013.37 | H13: 495.071 | I13: =(G13-G12)+(H13-H12) -> 1.769 | J13: =B13-C13 -> -0.5743 | K13: =D13*100/L13 -> 3.5084689 | L13: =M12 -> 118.81451 | M13: =L13*(1+K13/400)/(1+I13/100)-J13/4 -> 117.91682
A14: f+9 | B14: 19.775 | C14: 20.0845 | D14: 4.23208 | E14: 3.88557 | F14: 4.5319 | G14: 1014.21 | H14: 496.074 | I14: =(G14-G13)+(H14-H13) -> 1.843 | J14: =B14-C14 -> -0.3095 | K14: =D14*100/L14 -> 3.5890386 | L14: =M13 -> 117.91682 | M14: =L14*(1+K14/400)/(1+I14/100)-J14/4 -> 116.89918
A15: f+10 | B15: 19.9 | C15: 19.8898 | D15: 4.2981 | E15: 3.89286 | F15: 4.63641 | G15: 1015.09 | H15: 497.09 | I15: =(G15-G14)+(H15-H14) -> 1.896 | J15: =B15-C15 -> 0.0102 | K15: =D15*100/L15 -> 3.6767579 | L15: =M14 -> 116.89918 | M15: =L15*(1+K15/400)/(1+I15/100)-J15/4 -> 115.776
A16: f+11 | B16: 20.0469 | C16: 19.6704 | D16: 4.3654 | E16: 3.90904 | F16: 4.74161 | G16: 1016.01 | H16: 498.122 | I16: =(G16-G15)+(H16-H15) -> 1.952 | J16: =B16-C16 -> 0.3765 | K16: =D16*100/L16 -> 3.770557 | L16: =M15 -> 115.776 | M16: =L16*(1+K16/400)/(1+I16/100)-J16/4 -> 114.53565
A17: f+12 | B17: 20.2121 | C17: 19.4332 | D17: 4.43274 | E17: 3.94096 | F17: 4.85809 | G17: 1016.96 | H17: 499.168 | I17: =(G17-G16)+(H17-H16) -> 1.996 | J17: =B17-C17 -> 0.7789 | K17: =D17*100/L17 -> 3.8701837 | L17: =M16 -> 114.53565 | M17: =L17*(1+K17/400)/(1+I17/100)-J17/4 -> 113.18603
A18: f+13 | B18: 20.3919 | C18: 19.1834 | D18: 4.49947 | E18: 3.96408 | F18: 4.99296 | G18: 1017.92 | H18: 500.229 | I18: =(G18-G17)+(H18-H17) -> 2.021 | J18: =B18-C18 -> 1.2085 | K18: =D18*100/L18 -> 3.9752874 | L18: =M17 -> 113.18603 | M18: =L18*(1+K18/400)/(1+I18/100)-J18/4 -> 111.74431
... A25: f+20 | B25: 21.6321 | C25: 17.4488 | D25: 4.92276 | E25: 4.02741 | F25: 5.73599 | G25: 1024.53 | H25: 507.918 | I25: =(G25-G24)+(H25-H24) -> 2.04 | J25: =B25-C25 -> 4.1833 | K25: =D25*100/L25 -> 4.8440811 | L25: =M24 -> 101.62423 | M25: =L25*(1+K25/400)/(1+I25/100)-J25/4 -> 99.752801
A27: READ-OFF: DSVC (col D) is the BVAR's projected debt-service-to-GDP; the q16/q84 columns are its forecast band. The effective rate i_eff (col K) is what that debt service implies on the rolling debt stock, and the projected debt/GDP (col M) is the budget identity applied forward from d0. This is the exact path the app charts.

Sheet UK Overview
A1: UK FISCAL ACCOUNTING — RAW -> BVAR -> RECURSION -> PROJECTION
A3: THE TARGET CONCEPT
A4: User's level form | B4: B_t = Exp_t - Rev_t + (1 + i_eff_t)*B_{t-1}, then d_t = B_t / GDP_t. Exp = PRIMARY expenditure (EXCLUDES interest). Rev = revenue. i_eff = effective rate on the debt stock. B = debt stock (level). The interest cost sits entirely in the (1+i_eff)*B_{t-1} term. d = B/GDP.
A5: App's ratio form (per quarter) | B5: d_t = d_{t-1}*(1 + i_eff/400)/(1 + gNomQ/100) - pb/4 (% of GDP; i_eff %/yr; gNomQ %/quarter; pb = rev - primexp). This is the user's level form rewritten in ratio space and quarterised - the SAME identity. The 'Fiscal Arithmetic' sheet proves the two land on the identical debt/GDP, column by column.
A7: THE THREE BVAR FISCAL DRIVERS (estimated)
A8: FREV_GDP | B8: Revenue / GDP * 100 (% of GDP). BVAR 'lin' variable.
A9: FPEXP_GDP | B9: (Expenditure - interest) / GDP * 100 = PRIMARY expenditure / GDP (% of GDP). 'lin'.
A10: DSVC | B10: Debt service / GDP * 100 = net interest / LAGGED GDP (% of GDP). 'lin'. THIS is forecast by the BVAR; the effective rate i_eff is BACKED OUT from it as i_eff = DSVC*100 / d_{t-1}.
A11: (internal) EFFI | B11: Effective interest rate = net interest / LAGGED debt stock * 100 (% p.a.). DSVC = EFFI * d_{t-1}/100, i.e. debt service = the effective rate applied to last quarter's debt ratio.
A13: THE FIVE SHEETS PER COUNTRY
A14: Raw Data | B14: the raw series in levels, with charts.
A15: Construction | B15: builds FREV_GDP, FPEXP_GDP, EFFI and DSVC from the raw cells with LIVE formulas.
A16: Fiscal Arithmetic | B16: reconstructs HISTORICAL debt/GDP from the flows (back-cast check vs observed).
A17: Projection | B17: how the BVAR projects DSVC (debt service) and debt/GDP AHEAD, with 16/84 bands.
A19: RAW SERIES & SOURCES
A20: Raw series (role) | B20: Source ID / provenance, units
A21: public-sector revenue | B21: ONS: public-sector current receipts, GBPm quarterly LEVEL
A22: total managed expenditure | B22: ONS: total public-sector expenditure INCL. interest, GBPm quarterly LEVEL
A23: public-sector debt interest | B23: ONS: net public-sector debt interest, GBPm quarterly LEVEL
A24: gross debt stock | B24: ONS: public-sector gross debt, GBPm end-quarter STOCK
A25: nominal GDP | B25: ONS: nominal GDP, GBPm quarterly LEVEL
A27: UNIT CONVENTIONS
A28: SAAR (US flows) | B28: GDP/FGRECPT/FGEXPND/A091 are Seasonally-Adjusted ANNUAL RATES: each quarter already states an annual $-rate, so a ratio is flow_t / GDP_t with NO *4.
A29: Quarterly levels (UK flows) | B29: ONS revenue/expenditure/interest are quarterly LEVELS (GBP m, not annualised), so the ratio uses a 4-QUARTER TRAILING SUM: 4q-sum(flow)/4q-sum(GDP).
A30: % of GDP (annual ratio) | B30: FREV_GDP, FPEXP_GDP, DSVC are annual ratios, e.g. 18 means 18% of GDP. Carried in the BVAR as 'lin' (level) variables.
A31: Effective rate | B31: EFFI is %/year on the debt STOCK (e.g. 3 = 3%/yr); NOT the policy or market yield.
A32: Debt / GDP (d) | B32: d, d0 in %, e.g. 100 = 100% of GDP. This workbook's UK d0 = 96.2412%.
A33: Nominal growth gNomQ | B33: %/QUARTER. US: from SAAR GDP (already annual). UK: from the 4q-GDP base (same base the ratio uses). The forecast uses Delta(real 100*log GDP) + Delta(deflator 100*log).
A35: SPOT-CHECK vs the deployed BVAR app/public/data/bvar/UK: UK 2025Q4 (last history): FREV_GDP=39.4124, FPEXP_GDP=37.6083, DSVC=3.8142, d0=96.2412 - MATCH historical.json cols 16/17/18 and fiscal_meta.json exactly. All 40 quarters match to <1e-4. No COVID treatment applied. BVAR projects DSVC 4.21 -> 3.31% of GDP over 20 quarters (see UK Projection).

Sheet UK Raw Data
A1: UK RAW DATA - ONS quarterly LEVELS (GBP million, not annualised)
A3: Date | B3: revenue (GBPm, q-level) | C3: total_expenditure (GBPm) | D3: interest (GBPm, q-level) | E3: gross_debt (GBPm, stock) | F3: nominal_gdp (GBPm, q-level)
B4: ONS public-sector current receipts | C4: ONS total managed expenditure (incl. interest) | D4: ONS public-sector debt interest (net) | E4: ONS public-sector gross debt (end-quarter STOCK) | F4: ONS nominal GDP, quarterly level
A5: 2000-Q1 | B5: 106101 | C5: 88583 | D5: 7941 | E5: 353300 | F5: 273551
A6: 2000-Q2 | B6: 97108 | C6: 87401 | D6: 8806 | E6: 341800 | F6: 275103
A7: 2000-Q3 | B7: 101376 | C7: 90818 | D7: 8408 | E7: 326600 | F7: 277076
A8: 2000-Q4 | B8: 95606 | C8: 93164 | D8: 9090 | E8: 333300 | F8: 279029
A9: 2001-Q1 | B9: 112322 | C9: 94677 | D9: 8353 | E9: 322000 | F9: 283724
A10: 2001-Q2 | B10: 99956 | C10: 94300 | D10: 8130 | E10: 330300 | F10: 287603
A11: 2001-Q3 | B11: 103742 | C11: 95848 | D11: 7608 | E11: 324600 | F11: 289333
A12: 2001-Q4 | B12: 96971 | C12: 100049 | D12: 8185 | E12: 335500 | F12: 289882
A13: 2002-Q1 | B13: 111742 | C13: 102469 | D13: 7375 | E13: 330600 | F13: 293878
A14: 2002-Q2 | B14: 99718 | C14: 102328 | D14: 8018 | E14: 339100 | F14: 297001
A15: 2002-Q3 | B15: 105076 | C15: 104237 | D15: 6825 | E15: 343600 | F15: 299863
A16: 2002-Q4 | B16: 99790 | C16: 106936 | D16: 8443 | E16: 368700 | F16: 303904
... A108: 2025-Q4 | B108: 294399 | C108: 314524 | D108: 28690 | E108: 2925600 | F108: 769261

Sheet UK Construction
A1: UK CONSTRUCTION - BVAR fiscal inputs from raw cells (LIVE FORMULAS, 4q trailing sums)
A2: UK flows are quarterly LEVELS, so each ratio annualises via a 4-QUARTER TRAILING SUM (SUM over the current and prior 3 rows; the first few rows use the available <4 quarters, matching the pipeline). EFFI uses *4 (a quarterly interest vs a stock); contrast the US, already SAAR. The UK gets NO COVID treatment: raw == what enters the BVAR.
A4: Date | B4: 4q rev | C4: 4q primexp | D4: 4q GDP | E4: FREV_GDP (% GDP) | F4: FPEXP_GDP (% GDP) | G4: EFFI (% p.a.) | H4: d_t (% GDP) | I4: d_{t-1} (% GDP) | J4: DSVC (% GDP)
B5: = SUM(revenue, this + prior 3 q) | C5: = SUM(total_exp - interest, this + prior 3 q) | D5: = SUM(nominal_gdp, this + prior 3 q) | E5: FREV = 100 * 4qRev / 4qGDP | F5: FPEXP = 100 * 4qPrimexp / 4qGDP | G5: EFFI = 100 * 4 * interest_t / gross_debt_{t-1} | H5: d = 100 * gross_debt_t / 4qGDP_t | I5: = prior-row d_t (lagged debt ratio) | J5: DSVC = EFFI * d_{t-1}/100 = 100*4*interest_t/4qGDP_{t-1} (DEBT SERVICE)
A6: ='UK Raw Data'!A5 -> 2000-Q1 | B6: =SUM('UK Raw Data'!B5:B5) -> 106101 | C6: =SUM('UK Raw Data'!C5:C5)-SUM('UK Raw Data'!D5:D5) -> 80642 | D6: =SUM('UK Raw Data'!F5:F5) -> 273551 | E6: =100*B6/D6 -> 38.786552 | F6: =100*C6/D6 -> 29.479695 | G6: =100*4*'UK Raw Data'!D5/'UK Raw Data'!E5 -> 8.9906595 | H6: =100*'UK Raw Data'!E5/D6 -> 129.15325 | I6: =H6 -> 129.15325 | J6: =G6*I6/100 -> 11.611729
A7: ='UK Raw Data'!A6 -> 2000-Q2 | B7: =SUM('UK Raw Data'!B5:B6) -> 203209 | C7: =SUM('UK Raw Data'!C5:C6)-SUM('UK Raw Data'!D5:D6) -> 159237 | D7: =SUM('UK Raw Data'!F5:F6) -> 548654 | E7: =100*B7/D7 -> 37.037732 | F7: =100*C7/D7 -> 29.02321 | G7: =100*4*'UK Raw Data'!D6/'UK Raw Data'!E5 -> 9.9699972 | H7: =100*'UK Raw Data'!E6/D7 -> 62.297915 | I7: =H6 -> 129.15325 | J7: =G7*I7/100 -> 12.876575
A8: ='UK Raw Data'!A7 -> 2000-Q3 | B8: =SUM('UK Raw Data'!B5:B7) -> 304585 | C8: =SUM('UK Raw Data'!C5:C7)-SUM('UK Raw Data'!D5:D7) -> 241647 | D8: =SUM('UK Raw Data'!F5:F7) -> 825730 | E8: =100*B8/D8 -> 36.886755 | F8: =100*C8/D8 -> 29.264651 | G8: =100*4*'UK Raw Data'!D7/'UK Raw Data'!E6 -> 9.8396723 | H8: =100*'UK Raw Data'!E7/D8 -> 39.55288 | I8: =H7 -> 62.297915 | J8: =G8*I8/100 -> 6.1299107
A9: ='UK Raw Data'!A8 -> 2000-Q4 | B9: =SUM('UK Raw Data'!B5:B8) -> 400191 | C9: =SUM('UK Raw Data'!C5:C8)-SUM('UK Raw Data'!D5:D8) -> 325721 | D9: =SUM('UK Raw Data'!F5:F8) -> 1104759 | E9: =100*B9/D9 -> 36.224281 | F9: =100*C9/D9 -> 29.483444 | G9: =100*4*'UK Raw Data'!D8/'UK Raw Data'!E7 -> 11.132884 | H9: =100*'UK Raw Data'!E8/D9 -> 30.169476 | I9: =H8 -> 39.55288 | J9: =G9*I9/100 -> 4.4033764
A10: ='UK Raw Data'!A9 -> 2001-Q1 | B10: =SUM('UK Raw Data'!B6:B9) -> 406412 | C10: =SUM('UK Raw Data'!C6:C9)-SUM('UK Raw Data'!D6:D9) -> 331403 | D10: =SUM('UK Raw Data'!F6:F9) -> 1114932 | E10: =100*B10/D10 -> 36.45173 | F10: =100*C10/D10 -> 29.724055 | G10: =100*4*'UK Raw Data'!D9/'UK Raw Data'!E8 -> 10.024602 | H10: =100*'UK Raw Data'!E9/D10 -> 28.880685 | I10: =H9 -> 30.169476 | J10: =G10*I10/100 -> 3.02437
A11: ='UK Raw Data'!A10 -> 2001-Q2 | B11: =SUM('UK Raw Data'!B7:B10) -> 409260 | C11: =SUM('UK Raw Data'!C7:C10)-SUM('UK Raw Data'!D7:D10) -> 338978 | D11: =SUM('UK Raw Data'!F7:F10) -> 1127432 | E11: =100*B11/D11 -> 36.300194 | F11: =100*C11/D11 -> 30.066381 | G11: =100*4*'UK Raw Data'!D10/'UK Raw Data'!E9 -> 10.099379 | H11: =100*'UK Raw Data'!E10/D11 -> 29.296667 | I11: =H10 -> 28.880685 | J11: =G11*I11/100 -> 2.9167698
A12: ='UK Raw Data'!A11 -> 2001-Q3 | B12: =SUM('UK Raw Data'!B8:B11) -> 411626 | C12: =SUM('UK Raw Data'!C8:C11)-SUM('UK Raw Data'!D8:D11) -> 344808 | D12: =SUM('UK Raw Data'!F8:F11) -> 1139689 | E12: =100*B12/D12 -> 36.117397 | F12: =100*C12/D12 -> 30.254569 | G12: =100*4*'UK Raw Data'!D11/'UK Raw Data'!E10 -> 9.2134423 | H12: =100*'UK Raw Data'!E11/D12 -> 28.481454 | I12: =H11 -> 29.296667 | J12: =G12*I12/100 -> 2.6992315
A13: ='UK Raw Data'!A12 -> 2001-Q4 | B13: =SUM('UK Raw Data'!B9:B12) -> 412991 | C13: =SUM('UK Raw Data'!C9:C12)-SUM('UK Raw Data'!D9:D12) -> 352598 | D13: =SUM('UK Raw Data'!F9:F12) -> 1150542 | E13: =100*B13/D13 -> 35.895343 | F13: =100*C13/D13 -> 30.646252 | G13: =100*4*'UK Raw Data'!D12/'UK Raw Data'!E11 -> 10.08626 | H13: =100*'UK Raw Data'!E12/D13 -> 29.16017 | I13: =H12 -> 28.481454 | J13: =G13*I13/100 -> 2.8727135
A14: ='UK Raw Data'!A13 -> 2002-Q1 | B14: =SUM('UK Raw Data'!B10:B13) -> 412411 | C14: =SUM('UK Raw Data'!C10:C13)-SUM('UK Raw Data'!D10:D13) -> 361368 | D14: =SUM('UK Raw Data'!F10:F13) -> 1160696 | E14: =100*B14/D14 -> 35.531354 | F14: =100*C14/D14 -> 31.133734 | G14: =100*4*'UK Raw Data'!D13/'UK Raw Data'!E12 -> 8.7928465 | H14: =100*'UK Raw Data'!E13/D14 -> 28.48291 | I14: =H13 -> 29.16017 | J14: =G14*I14/100 -> 2.564009
A15: ='UK Raw Data'!A14 -> 2002-Q2 | B15: =SUM('UK Raw Data'!B11:B14) -> 412173 | C15: =SUM('UK Raw Data'!C11:C14)-SUM('UK Raw Data'!D11:D14) -> 369508 | D15: =SUM('UK Raw Data'!F11:F14) -> 1170094 | E15: =100*B15/D15 -> 35.225631 | F15: =100*C15/D15 -> 31.579343 | G15: =100*4*'UK Raw Data'!D14/'UK Raw Data'!E13 -> 9.7011494 | H15: =100*'UK Raw Data'!E14/D15 -> 28.980578 | I15: =H14 -> 28.48291 | J15: =G15*I15/100 -> 2.7631697
A16: ='UK Raw Data'!A15 -> 2002-Q3 | B16: =SUM('UK Raw Data'!B12:B15) -> 413507 | C16: =SUM('UK Raw Data'!C12:C15)-SUM('UK Raw Data'!D12:D15) -> 378680 | D16: =SUM('UK Raw Data'!F12:F15) -> 1180624 | E16: =100*B16/D16 -> 35.024445 | F16: =100*C16/D16 -> 32.074564 | G16: =100*4*'UK Raw Data'!D15/'UK Raw Data'!E14 -> 8.0507225 | H16: =100*'UK Raw Data'!E15/D16 -> 29.103254 | I16: =H15 -> 28.980578 | J16: =G16*I16/100 -> 2.3331459
A17: ='UK Raw Data'!A16 -> 2002-Q4 | B17: =SUM('UK Raw Data'!B13:B16) -> 416326 | C17: =SUM('UK Raw Data'!C13:C16)-SUM('UK Raw Data'!D13:D16) -> 385309 | D17: =SUM('UK Raw Data'!F13:F16) -> 1194646 | E17: =100*B17/D17 -> 34.849319 | F17: =100*C17/D17 -> 32.252985 | G17: =100*4*'UK Raw Data'!D16/'UK Raw Data'!E15 -> 9.8288708 | H17: =100*'UK Raw Data'!E16/D17 -> 30.862699 | I17: =H16 -> 29.103254 | J17: =G17*I17/100 -> 2.8605212
A18: ='UK Raw Data'!A17 -> 2003-Q1 | B18: =SUM('UK Raw Data'!B14:B17) -> 417783 | C18: =SUM('UK Raw Data'!C14:C17)-SUM('UK Raw Data'!D14:D17) -> 395165 | D18: =SUM('UK Raw Data'!F14:F17) -> 1208344 | E18: =100*B18/D18 -> 34.57484 | F18: =100*C18/D18 -> 32.703022 | G18: =100*4*'UK Raw Data'!D17/'UK Raw Data'!E16 -> 8.040141 | H18: =100*'UK Raw Data'!E17/D18 -> 30.554213 | I18: =H17 -> 30.862699 | J18: =G18*I18/100 -> 2.4814045
A19: ='UK Raw Data'!A18 -> 2003-Q2 | B19: =SUM('UK Raw Data'!B15:B18) -> 424791 | C19: =SUM('UK Raw Data'!C15:C18)-SUM('UK Raw Data'!D15:D18) -> 406087 | D19: =SUM('UK Raw Data'!F15:F18) -> 1224966 | E19: =100*B19/D19 -> 34.677779 | F19: =100*C19/D19 -> 33.150879 | G19: =100*4*'UK Raw Data'!D18/'UK Raw Data'!E17 -> 9.0747562 | H19: =100*'UK Raw Data'!E18/D19 -> 30.653912 | I19: =H18 -> 30.554213 | J19: =G19*I19/100 -> 2.7727204
A20: ='UK Raw Data'!A19 -> 2003-Q3 | B20: =SUM('UK Raw Data'!B16:B19) -> 430638 | C20: =SUM('UK Raw Data'!C16:C19)-SUM('UK Raw Data'!D16:D19) -> 416756 | D20: =SUM('UK Raw Data'!F16:F19) -> 1243978 | E20: =100*B20/D20 -> 34.617815 | F20: =100*C20/D20 -> 33.501879 | G20: =100*4*'UK Raw Data'!D19/'UK Raw Data'!E18 -> 8.1523302 | H20: =100*'UK Raw Data'!E19/D20 -> 30.820481 | I20: =H19 -> 30.653912 | J20: =G20*I20/100 -> 2.4990081
... A109: ='UK Raw Data'!A108 -> 2025-Q4 | B109: =SUM('UK Raw Data'!B105:B108) -> 1198083 | C109: =SUM('UK Raw Data'!C105:C108)-SUM('UK Raw Data'!D105:D108) -> 1143241 | D109: =SUM('UK Raw Data'!F105:F108) -> 3039861 | E109: =100*B109/D109 -> 39.412427 | F109: =100*C109/D109 -> 37.608331 | G109: =100*4*'UK Raw Data'!D108/'UK Raw Data'!E107 -> 3.9390403 | H109: =100*'UK Raw Data'!E108/D109 -> 96.241243 | I109: =H108 -> 96.831586 | J109: =G109*I109/100 -> 3.8142352

Sheet UK Fiscal Arithmetic
A1: UK FISCAL ARITHMETIC - decompose the OBSERVED debt/GDP change (LIVE)
A2: A one-step decomposition of the OBSERVED debt change: each row rolls forward from the OBSERVED d_{t-1}, so it is an exact quarter-by-quarter accounting. Same budget identity in two forms: RATIO form (the app): d_t = d_{t-1}*(1+i_eff/400)/(1+gNomQ/100) - pb/4 + sfa/4 LEVEL form (your concept): B_t = (1+i_eff/400)*B_{t-1} - PB$_t + SFA$_t , then d_t = B_t/GDPann_t*100. pb = FREV - FPEXP. SFA (col H) is a COMPUTED residual = the part of the observed debt change NOT explained by interest+growth+primary balance (the deficit-debt discrepancy: valuation, below-the-line financing). It is NOT a zero input - it is informative. With it, BOTH forms reproduce OBSERVED debt/GDP to the last digit (col L = 0).
A4: Date | B4: pb (% GDP) | C4: DSVC = interest (% GDP) | D4: i_eff (% p.a.) | E4: gNomQ (% / quarter) | F4: d_{t-1} OBSERVED (% GDP) | G4: snowball (pp) | H4: SFA (% GDP, residual) | I4: d_t RATIO form (% GDP) | J4: B_t LEVEL ($/GBP) | K4: d_t from LEVEL (% GDP) | L4: OBSERVED d_t (% GDP) | M4: recon - observed (pp)
B5: primary balance = FREV - FPEXP (FPEXP as it ENTERED the BVAR) | C5: debt service from Construction (the estimated driver) | D5: effective rate, BACKED OUT: i_eff = DSVC*100 / d_{t-1} | E5: US: 100*(GDP_t/GDP_{t-1}-1), SAAR. UK: 100*(4qGDP_t/4qGDP_{t-1}-1) | F5: lagged OBSERVED debt ratio (the decomposition starts from data each step) | G5: = [(1+i_eff/400)/(1+gNomQ/100) - 1] * d_{t-1} (automatic debt dynamics) | H5: = 4*(d_obs_t - d_{t-1} - snowball + pb/4) (deficit-debt discrepancy, COMPUTED) | I5: = d_{t-1}(1+i_eff/400)/(1+gNomQ/100) - pb/4 + sfa/4 | J5: = (1+i_eff/400)*B_{t-1} - PB$_t + SFA$_t ; B_{t-1}=d_{t-1}/100*GDPann_{t-1} | K5: = B_t / GDPann_t * 100 (must equal the RATIO-form d_t) | L5: US: GFDEGDQ188S; UK: 100*gross_debt_t/4qGDP_t (back-cast TARGET) | M5: = d_t(ratio) - observed (the CHECK, ~0 with the SFA residual)
A6: ='UK Construction'!A6 -> 2000-Q1 | B6: ='UK Construction'!E6-'UK Construction'!F6 -> 9.3068569 | C6: ='UK Construction'!J6 -> 11.611729 | D6: =C6*100/F6 -> 8.9906595 | E6: =0 -> 0 | F6: ='UK Construction'!H6 -> 129.15325 | G6: =((1+D6/400)/(1+E6/100)-1)*F6 -> 2.9029322 | H6: =4*(L6-F6-G6+B6/4) -> -2.3048719 | I6: =F6*(1+D6/400)/(1+E6/100)-B6/4+H6/4 -> 129.15325 | J6: =(1+D6/400)*(F6/100*'UK Construction'!D6)-B6/100*'UK Construction'!D6/4+H6/100*'UK Construction'!D6/4 -> 353300 | K6: =J6/'UK Construction'!D6*100 -> 129.15325 | L6: ='UK Construction'!H6 -> 129.15325 | M6: =I6-L6 -> 0
A7: ='UK Construction'!A7 -> 2000-Q2 | B7: ='UK Construction'!E7-'UK Construction'!F7 -> 8.0145228 | C7: ='UK Construction'!J7 -> 12.876575 | D7: =C7*100/F7 -> 9.9699972 | E7: =100*('UK Construction'!D7/'UK Construction'!D6-1) -> 100.56735 | F7: ='UK Construction'!H6 -> 129.15325 | G7: =((1+D7/400)/(1+E7/100)-1)*F7 -> -63.154275 | H7: =4*(L7-F7-G7+B7/4) -> -6.7897072 | I7: =F7*(1+D7/400)/(1+E7/100)-B7/4+H7/4 -> 62.297915 | J7: =(1+D7/400)*(F7/100*'UK Construction'!D6)-B7/100*'UK Construction'!D7/4+H7/100*'UK Construction'!D7/4 -> 341800 | K7: =J7/'UK Construction'!D7*100 -> 62.297915 | L7: ='UK Construction'!H7 -> 62.297915 | M7: =I7-L7 -> 0
A8: ='UK Construction'!A8 -> 2000-Q3 | B8: ='UK Construction'!E8-'UK Construction'!F8 -> 7.6221041 | C8: ='UK Construction'!J8 -> 6.1299107 | D8: =C8*100/F8 -> 9.8396723 | E8: =100*('UK Construction'!D8/'UK Construction'!D7-1) -> 50.501044 | F8: ='UK Construction'!H7 -> 62.297915 | G8: =((1+D8/400)/(1+E8/100)-1)*F8 -> -19.885988 | H8: =4*(L8-F8-G8+B8/4) -> -3.8140797 | I8: =F8*(1+D8/400)/(1+E8/100)-B8/4+H8/4 -> 39.55288 | J8: =(1+D8/400)*(F8/100*'UK Construction'!D7)-B8/100*'UK Construction'!D8/4+H8/100*'UK Construction'!D8/4 -> 326600 | K8: =J8/'UK Construction'!D8*100 -> 39.55288 | L8: ='UK Construction'!H8 -> 39.55288 | M8: =I8-L8 -> 0
A9: ='UK Construction'!A9 -> 2000-Q4 | B9: ='UK Construction'!E9-'UK Construction'!F9 -> 6.7408367 | C9: ='UK Construction'!J9 -> 4.4033764 | D9: =C9*100/F9 -> 11.132884 | E9: =100*('UK Construction'!D9/'UK Construction'!D8-1) -> 33.791796 | F9: ='UK Construction'!H8 -> 39.55288 | G9: =((1+D9/400)/(1+E9/100)-1)*F9 -> -9.1670678 | H9: =4*(L9-F9-G9+B9/4) -> 5.8754896 | I9: =F9*(1+D9/400)/(1+E9/100)-B9/4+H9/4 -> 30.169476 | J9: =(1+D9/400)*(F9/100*'UK Construction'!D8)-B9/100*'UK Construction'!D9/4+H9/100*'UK Construction'!D9/4 -> 333300 | K9: =J9/'UK Construction'!D9*100 -> 30.169476 | L9: ='UK Construction'!H9 -> 30.169476 | M9: =I9-L9 -> 0
A10: ='UK Construction'!A10 -> 2001-Q1 | B10: ='UK Construction'!E10-'UK Construction'!F10 -> 6.7276749 | C10: ='UK Construction'!J10 -> 3.02437 | D10: =C10*100/F10 -> 10.024602 | E10: =100*('UK Construction'!D10/'UK Construction'!D9-1) -> 0.92083432 | F10: ='UK Construction'!H9 -> 30.169476 | G10: =((1+D10/400)/(1+E10/100)-1)*F10 -> 0.47391762 | H10: =4*(L10-F10-G10+B10/4) -> -0.32315872 | I10: =F10*(1+D10/400)/(1+E10/100)-B10/4+H10/4 -> 28.880685 | J10: =(1+D10/400)*(F10/100*'UK Construction'!D9)-B10/100*'UK Construction'!D10/4+H10/100*'UK Construction'!D10/4 -> 322000 | K10: =J10/'UK Construction'!D10*100 -> 28.880685 | L10: ='UK Construction'!H10 -> 28.880685 | M10: =I10-L10 -> 0
A11: ='UK Construction'!A11 -> 2001-Q2 | B11: ='UK Construction'!E11-'UK Construction'!F11 -> 6.2338128 | C11: ='UK Construction'!J11 -> 2.9167698 | D11: =C11*100/F11 -> 10.099379 | E11: =100*('UK Construction'!D11/'UK Construction'!D10-1) -> 1.1211446 | F11: ='UK Construction'!H10 -> 28.880685 | G11: =((1+D11/400)/(1+E11/100)-1)*F11 -> 0.4009035 | H11: =4*(L11-F11-G11+B11/4) -> 6.2941268 | I11: =F11*(1+D11/400)/(1+E11/100)-B11/4+H11/4 -> 29.296667 | J11: =(1+D11/400)*(F11/100*'UK Construction'!D10)-B11/100*'UK Construction'!D11/4+H11/100*'UK Construction'!D11/4 -> 330300 | K11: =J11/'UK Construction'!D11*100 -> 29.296667 | L11: ='UK Construction'!H11 -> 29.296667 | M11: =I11-L11 -> 0
A12: ='UK Construction'!A12 -> 2001-Q3 | B12: ='UK Construction'!E12-'UK Construction'!F12 -> 5.8628275 | C12: ='UK Construction'!J12 -> 2.6992315 | D12: =C12*100/F12 -> 9.2134423 | E12: =100*('UK Construction'!D12/'UK Construction'!D11-1) -> 1.0871609 | F12: ='UK Construction'!H11 -> 29.296667 | G12: =((1+D12/400)/(1+E12/100)-1)*F12 -> 0.35247401 | H12: =4*(L12-F12-G12+B12/4) -> 1.1920796 | I12: =F12*(1+D12/400)/(1+E12/100)-B12/4+H12/4 -> 28.481454 | J12: =(1+D12/400)*(F12/100*'UK Construction'!D11)-B12/100*'UK Construction'!D12/4+H12/100*'UK Construction'!D12/4 -> 324600 | K12: =J12/'UK Construction'!D12*100 -> 28.481454 | L12: ='UK Construction'!H12 -> 28.481454 | M12: =I12-L12 -> 0
A13: ='UK Construction'!A13 -> 2001-Q4 | B13: ='UK Construction'!E13-'UK Construction'!F13 -> 5.2490913 | C13: ='UK Construction'!J13 -> 2.8727135 | D13: =C13*100/F13 -> 10.08626 | E13: =100*('UK Construction'!D13/'UK Construction'!D12-1) -> 0.95227733 | F13: ='UK Construction'!H12 -> 28.481454 | G13: =((1+D13/400)/(1+E13/100)-1)*F13 -> 0.44273984 | H13: =4*(L13-F13-G13+B13/4) -> 6.1929943 | I13: =F13*(1+D13/400)/(1+E13/100)-B13/4+H13/4 -> 29.16017 | J13: =(1+D13/400)*(F13/100*'UK Construction'!D12)-B13/100*'UK Construction'!D13/4+H13/100*'UK Construction'!D13/4 -> 335500 | K13: =J13/'UK Construction'!D13*100 -> 29.16017 | L13: ='UK Construction'!H13 -> 29.16017 | M13: =I13-L13 -> 0
A14: ='UK Construction'!A14 -> 2002-Q1 | B14: ='UK Construction'!E14-'UK Construction'!F14 -> 4.39762 | C14: ='UK Construction'!J14 -> 2.564009 | D14: =C14*100/F14 -> 8.7928465 | E14: =100*('UK Construction'!D14/'UK Construction'!D13-1) -> 0.88254058 | F14: ='UK Construction'!H13 -> 29.16017 | G14: =((1+D14/400)/(1+E14/100)-1)*F14 -> 0.38029565 | H14: =4*(L14-F14-G14+B14/4) -> 0.16739956 | I14: =F14*(1+D14/400)/(1+E14/100)-B14/4+H14/4 -> 28.48291 | J14: =(1+D14/400)*(F14/100*'UK Construction'!D13)-B14/100*'UK Construction'!D14/4+H14/100*'UK Construction'!D14/4 -> 330600 | K14: =J14/'UK Construction'!D14*100 -> 28.48291 | L14: ='UK Construction'!H14 -> 28.48291 | M14: =I14-L14 -> 0
A15: ='UK Construction'!A15 -> 2002-Q2 | B15: ='UK Construction'!E15-'UK Construction'!F15 -> 3.6462882 | C15: ='UK Construction'!J15 -> 2.7631697 | D15: =C15*100/F15 -> 9.7011494 | E15: =100*('UK Construction'!D15/'UK Construction'!D14-1) -> 0.8096866 | F15: ='UK Construction'!H14 -> 28.48291 | G15: =((1+D15/400)/(1+E15/100)-1)*F15 -> 0.4564741 | H15: =4*(L15-F15-G15+B15/4) -> 3.8110613 | I15: =F15*(1+D15/400)/(1+E15/100)-B15/4+H15/4 -> 28.980578 | J15: =(1+D15/400)*(F15/100*'UK Construction'!D14)-B15/100*'UK Construction'!D15/4+H15/100*'UK Construction'!D15/4 -> 339100 | K15: =J15/'UK Construction'!D15*100 -> 28.980578 | L15: ='UK Construction'!H15 -> 28.980578 | M15: =I15-L15 -> 0
A16: ='UK Construction'!A16 -> 2002-Q3 | B16: ='UK Construction'!E16-'UK Construction'!F16 -> 2.9498807 | C16: ='UK Construction'!J16 -> 2.3331459 | D16: =C16*100/F16 -> 8.0507225 | E16: =100*('UK Construction'!D16/'UK Construction'!D15-1) -> 0.8999277 | F16: ='UK Construction'!H15 -> 28.980578 | G16: =((1+D16/400)/(1+E16/100)-1)*F16 -> 0.319606 | H16: =4*(L16-F16-G16+B16/4) -> 2.1621617 | I16: =F16*(1+D16/400)/(1+E16/100)-B16/4+H16/4 -> 29.103254 | J16: =(1+D16/400)*(F16/100*'UK Construction'!D15)-B16/100*'UK Construction'!D16/4+H16/100*'UK Construction'!D16/4 -> 343600 | K16: =J16/'UK Construction'!D16*100 -> 29.103254 | L16: ='UK Construction'!H16 -> 29.103254 | M16: =I16-L16 -> 0
A17: ='UK Construction'!A17 -> 2002-Q4 | B17: ='UK Construction'!E17-'UK Construction'!F17 -> 2.596334 | C17: ='UK Construction'!J17 -> 2.8605212 | D17: =C17*100/F17 -> 9.8288708 | E17: =100*('UK Construction'!D17/'UK Construction'!D16-1) -> 1.187677 | F17: ='UK Construction'!H16 -> 29.103254 | G17: =((1+D17/400)/(1+E17/100)-1)*F17 -> 0.36514095 | H17: =4*(L17-F17-G17+B17/4) -> 8.173551 | I17: =F17*(1+D17/400)/(1+E17/100)-B17/4+H17/4 -> 30.862699 | J17: =(1+D17/400)*(F17/100*'UK Construction'!D16)-B17/100*'UK Construction'!D17/4+H17/100*'UK Construction'!D17/4 -> 368700 | K17: =J17/'UK Construction'!D17*100 -> 30.862699 | L17: ='UK Construction'!H17 -> 30.862699 | M17: =I17-L17 -> 0
A18: ='UK Construction'!A18 -> 2003-Q1 | B18: ='UK Construction'!E18-'UK Construction'!F18 -> 1.871818 | C18: ='UK Construction'!J18 -> 2.4814045 | D18: =C18*100/F18 -> 8.040141 | E18: =100*('UK Construction'!D18/'UK Construction'!D17-1) -> 1.1466158 | F18: ='UK Construction'!H17 -> 30.862699 | G18: =((1+D18/400)/(1+E18/100)-1)*F18 -> 0.26345374 | H18: =4*(L18-F18-G18+B18/4) -> -0.41594116 | I18: =F18*(1+D18/400)/(1+E18/100)-B18/4+H18/4 -> 30.554213 | J18: =(1+D18/400)*(F18/100*'UK Construction'!D17)-B18/100*'UK Construction'!D18/4+H18/100*'UK Construction'!D18/4 -> 369200 | K18: =J18/'UK Construction'!D18*100 -> 30.554213 | L18: ='UK Construction'!H18 -> 30.554213 | M18: =I18-L18 -> 0
... A109: ='UK Construction'!A109 -> 2025-Q4 | B109: ='UK Construction'!E109-'UK Construction'!F109 -> 1.8040956 | C109: ='UK Construction'!J109 -> 3.8142352 | D109: =C109*100/F109 -> 3.9390403 | E109: =100*('UK Construction'!D109/'UK Construction'!D108-1) -> 1.0347226 | F109: ='UK Construction'!H108 -> 96.831586 | G109: =((1+D109/400)/(1+E109/100)-1)*F109 -> -0.047884073 | H109: =4*(L109-F109-G109+B109/4) -> -0.36574041 | I109: =F109*(1+D109/400)/(1+E109/100)-B109/4+H109/4 -> 96.241243 | J109: =(1+D109/400)*(F109/100*'UK Construction'!D108)-B109/100*'UK Construction'!D109/4+H109/100*'UK Construction'!D109/4 -> 2925600 | K109: =J109/'UK Construction'!D109*100 -> 96.241243 | L109: ='UK Construction'!H109 -> 96.241243 | M109: =I109-L109 -> 0
A111: EQUIVALENCE: the RATIO-form d_t (col I) and the LEVEL-form d_t (col K) are identical to display precision - your level recursion B_t=(1+i_eff)B_{t-1}-(Exp-Rev)+SFA and the app's ratio recursion are the SAME identity. col M (recon - observed) is ~0 because the SFA residual (col H) closes the identity onto observed. SFA itself is the informative deficit-debt discrepancy (financial transactions / valuation / below-the-line) - read it as a column in its own right.

Sheet UK Projection
A1: UK PROJECTION - how the BVAR forecasts debt service & debt/GDP AHEAD
A2: The orange columns (FREV, FPEXP, DSVC and its 16/84 bands, plus the forecast 100*log GDP and deflator) ARE the deployed BVAR output, app/public/data/bvar/UK/baseline_levels.json, over the 20-quarter forecast starting the quarter after the last history. The BVAR forecasts DSVC (debt service) DIRECTLY as a 'lin' variable. From it the white columns back out the effective rate and roll the debt forward with LIVE formulas, exactly as fiscalAccounting.ts does: i_eff = DSVC*100/d_{t-1} ; gNomQ = Delta(100*log GDP) + Delta(100*log deflator) ; pb = FREV - FPEXP ; d_t = d_{t-1}*(1+i_eff/400)/(1+gNomQ/100) - pb/4. The debt-service $ cost = DSVC/100 * GDP grows as both DSVC (the rate*stock effect) and GDP rise. The 16/84 DSVC band shows the BVAR's forecast uncertainty on the debt-service cost.
A4: Fcst q | B4: FREV_GDP (% GDP) | C4: FPEXP_GDP (% GDP) | D4: DSVC (% GDP) | E4: DSVC q16 (% GDP) | F4: DSVC q84 (% GDP) | G4: 100*log GDP | H4: 100*log deflator | I4: gNomQ (% / q) | J4: pb (% GDP) | K4: i_eff (% p.a.) | L4: d_{t-1} (% GDP) | M4: d_t (% GDP)
B5: BVAR forecast, baseline_levels | C5: BVAR forecast, baseline_levels | D5: BVAR forecast debt service (the estimated driver) | E5: BVAR 16th pctile band | F5: BVAR 84th pctile band | G5: BVAR forecast real GDP (level space) | H5: BVAR forecast GDP deflator (level space) | I5: = Delta(100*log GDP) + Delta(100*log deflator) (nominal growth) | J5: = FREV - FPEXP (primary balance) | K5: = DSVC*100 / d_{t-1} (effective rate, backed out) | L5: lagged debt ratio (seed = d0 = last observed debt/GDP) | M5: = d_{t-1}(1+i_eff/400)/(1+gNomQ/100) - pb/4 (PROJECTED debt/GDP)
A6: f+1 | B6: 39.326 | C6: 37.8503 | D6: 4.20922 | E6: 3.25349 | F6: 5.12381 | G6: 1347.02 | H6: 494.625 | I6: =(G6-1346.75)+(H6-494.021) -> 0.874 | J6: =B6-C6 -> 1.4757 | K6: =D6*100/L6 -> 4.3736135 | L6: =96.241243 -> 96.241243 | M6: =L6*(1+K6/400)/(1+I6/100)-J6/4 -> 96.081645
A7: f+2 | B7: 39.2984 | C7: 38.0569 | D7: 3.94021 | E7: 2.7327 | F7: 5.10054 | G7: 1347.38 | H7: 495.07 | I7: =(G7-G6)+(H7-H6) -> 0.805 | J7: =B7-C7 -> 1.2415 | K7: =D7*100/L7 -> 4.1008977 | L7: =M6 -> 96.081645 | M7: =L7*(1+K7/400)/(1+I7/100)-J7/4 -> 95.981176
A8: f+3 | B8: 39.2271 | C8: 38.2523 | D8: 4.00228 | E8: 2.37488 | F8: 5.38296 | G8: 1347.77 | H8: 495.652 | I8: =(G8-G7)+(H8-H7) -> 0.972 | J8: =B8-C8 -> 0.9748 | K8: =D8*100/L8 -> 4.1698593 | L8: =M7 -> 95.981176 | M8: =L8*(1+K8/400)/(1+I8/100)-J8/4 -> 95.804457
A9: f+4 | B9: 39.1666 | C9: 38.406 | D9: 3.82057 | E9: 2.21108 | F9: 5.50767 | G9: 1348.18 | H9: 496.156 | I9: =(G9-G8)+(H9-H8) -> 0.914 | J9: =B9-C9 -> 0.7606 | K9: =D9*100/L9 -> 3.9878833 | L9: =M8 -> 95.804457 | M9: =L9*(1+K9/400)/(1+I9/100)-J9/4 -> 95.693077
A10: f+5 | B10: 39.1029 | C10: 38.5185 | D10: 3.78633 | E10: 1.81765 | F10: 5.64089 | G10: 1348.59 | H10: 496.77 | I10: =(G10-G9)+(H10-H9) -> 1.024 | J10: =B10-C10 -> 0.5844 | K10: =D10*100/L10 -> 3.9567439 | L10: =M9 -> 95.693077 | M10: =L10*(1+K10/400)/(1+I10/100)-J10/4 -> 95.514
A11: f+6 | B11: 39.055 | C11: 38.6035 | D11: 3.65596 | E11: 1.58561 | F11: 5.78978 | G11: 1349.01 | H11: 497.365 | I11: =(G11-G10)+(H11-H10) -> 1.015 | J11: =B11-C11 -> 0.4515 | K11: =D11*100/L11 -> 3.8276692 | L11: =M10 -> 95.514 | M11: =L11*(1+K11/400)/(1+I11/100)-J11/4 -> 95.346206
A12: f+7 | B12: 39.012 | C12: 38.6774 | D12: 3.62247 | E12: 1.47366 | F12: 5.84045 | G12: 1349.42 | H12: 498.008 | I12: =(G12-G11)+(H12-H11) -> 1.053 | J12: =B12-C12 -> 0.3346 | K12: =D12*100/L12 -> 3.7992807 | L12: =M11 -> 95.346206 | M12: =L12*(1+K12/400)/(1+I12/100)-J12/4 -> 95.165203
A13: f+8 | B13: 38.9819 | C13: 38.7489 | D13: 3.54003 | E13: 1.31501 | F13: 6.05293 | G13: 1349.82 | H13: 498.642 | I13: =(G13-G12)+(H13-H12) -> 1.034 | J13: =B13-C13 -> 0.233 | K13: =D13*100/L13 -> 3.7198786 | L13: =M12 -> 95.165203 | M13: =L13*(1+K13/400)/(1+I13/100)-J13/4 -> 95.008965
A14: f+9 | B14: 38.9577 | C14: 38.8177 | D14: 3.5033 | E14: 0.89768 | F14: 6.07453 | G14: 1350.21 | H14: 499.302 | I14: =(G14-G13)+(H14-H13) -> 1.05 | J14: =B14-C14 -> 0.14 | K14: =D14*100/L14 -> 3.6873362 | L14: =M13 -> 95.008965 | M14: =L14*(1+K14/400)/(1+I14/100)-J14/4 -> 94.853461
A15: f+10 | B15: 38.9419 | C15: 38.8852 | D15: 3.4484 | E15: 0.959182 | F15: 6.20895 | G15: 1350.59 | H15: 499.96 | I15: =(G15-G14)+(H15-H14) -> 1.038 | J15: =B15-C15 -> 0.0567 | K15: =D15*100/L15 -> 3.6355025 | L15: =M14 -> 94.853461 | M15: =L15*(1+K15/400)/(1+I15/100)-J15/4 -> 94.718066
A16: f+11 | B16: 38.9295 | C16: 38.9505 | D16: 3.41733 | E16: 0.660193 | F16: 6.1112 | G16: 1350.96 | H16: 500.632 | I16: =(G16-G15)+(H16-H15) -> 1.042 | J16: =B16-C16 -> -0.021 | K16: =D16*100/L16 -> 3.6078967 | L16: =M15 -> 94.718066 | M16: =L16*(1+K16/400)/(1+I16/100)-J16/4 -> 94.592054
A17: f+12 | B17: 38.9217 | C17: 39.0127 | D17: 3.3808 | E17: 0.574557 | F17: 6.21303 | G17: 1351.34 | H17: 501.305 | I17: =(G17-G16)+(H17-H16) -> 1.053 | J17: =B17-C17 -> -0.091 | K17: =D17*100/L17 -> 3.5740846 | L17: =M16 -> 94.592054 | M17: =L17*(1+K17/400)/(1+I17/100)-J17/4 -> 94.465521
A18: f+13 | B18: 38.9167 | C18: 39.0711 | D18: 3.35806 | E18: 0.248045 | F18: 6.25392 | G18: 1351.71 | H18: 501.986 | I18: =(G18-G17)+(H18-H17) -> 1.051 | J18: =B18-C18 -> -0.1544 | K18: =D18*100/L18 -> 3.5547996 | L18: =M17 -> 94.465521 | M18: =L18*(1+K18/400)/(1+I18/100)-J18/4 -> 94.352398
... A25: f+20 | B25: 38.9536 | C25: 39.3716 | D25: 3.30741 | E25: 0.0223507 | F25: 7.1005 | G25: 1354.28 | H25: 506.862 | I25: =(G25-G24)+(H25-H24) -> 1.067 | J25: =B25-C25 -> -0.418 | K25: =D25*100/L25 -> 3.5259837 | L25: =M24 -> 93.801056 | M25: =L25*(1+K25/400)/(1+I25/100)-J25/4 -> 93.733389
A27: READ-OFF: DSVC (col D) is the BVAR's projected debt-service-to-GDP; the q16/q84 columns are its forecast band. The effective rate i_eff (col K) is what that debt service implies on the rolling debt stock, and the projected debt/GDP (col M) is the budget identity applied forward from d0. This is the exact path the app charts.
